Workbook

Sheet Expense Data
A1: SME Expense Tracker 2024 | Raw Data
A2: # | B2: Date | C2: Month | D2: Qtr | E2: Category | F2: Department | G2: Description | H2: Budget (£) | I2: Actual (£) | J2: Variance (£) | K2: Var % | L2: Status
A3: 1 | B3: 2024-01-01 | C3: Jan | D3: Q1 | E3: Salaries | F3: Marketing | G3: Monthly payroll | H3: 9125.05 | I3: 10090.5 | J3: =I3-H3 -> 965.45 | K3: =IFERROR((I3-H3)/H3,0) -> 0.10580216 | L3: =IF(J3>0,"Over Budget",IF(J3<0,"Under Budget","On Budget")) -> Over Budget
A4: 2 | B4: 2024-01-01 | C4: Jan | D4: Q1 | E4: Rent & Utilities | F4: Marketing | G4: Office rent | H4: 4176.7 | I4: 3257.81 | J4: =I4-H4 -> -918.89 | K4: =IFERROR((I4-H4)/H4,0) -> -0.22000383 | L4: =IF(J4>0,"Over Budget",IF(J4<0,"Under Budget","On Budget")) -> Under Budget
A5: 3 | B5: 2024-01-01 | C5: Jan | D5: Q1 | E5: IT & Software | F5: HR | G5: SaaS subscriptions | H5: 1268.53 | I5: 1492.22 | J5: =I5-H5 -> 223.69 | K5: =IFERROR((I5-H5)/H5,0) -> 0.17633797 | L5: =IF(J5>0,"Over Budget",IF(J5<0,"Under Budget","On Budget")) -> Over Budget
A6: 4 | B6: 2024-01-01 | C6: Jan | D6: Q1 | E6: Marketing | F6: Operations | G6: SEO & PPC | H6: 3096.51 | I6: 2741.45 | J6: =I6-H6 -> -355.06 | K6: =IFERROR((I6-H6)/H6,0) -> -0.11466457 | L6: =IF(J6>0,"Over Budget",IF(J6<0,"Under Budget","On Budget")) -> Under Budget
A7: 5 | B7: 2024-01-01 | C7: Jan | D7: Q1 | E7: Travel | F7: Sales | G7: Hotel & accommodation | H7: 1307.12 | I7: 995.36 | J7: =I7-H7 -> -311.76 | K7: =IFERROR((I7-H7)/H7,0) -> -0.23850909 | L7: =IF(J7>0,"Over Budget",IF(J7<0,"Under Budget","On Budget")) -> Under Budget
A8: 6 | B8: 2024-01-01 | C8: Jan | D8: Q1 | E8: Office Supplies | F8: Sales | G8: Coffee etc. | H8: 440.18 | I8: 485.88 | J8: =I8-H8 -> 45.7 | K8: =IFERROR((I8-H8)/H8,0) -> 0.10382116 | L8: =IF(J8>0,"Over Budget",IF(J8<0,"Under Budget","On Budget")) -> Over Budget
A9: 7 | B9: 2024-01-01 | C9: Jan | D9: Q1 | E9: Professional Services | F9: Finance | G9: Legal fees | H9: 2050.41 | I9: 2587.36 | J9: =I9-H9 -> 536.95 | K9: =IFERROR((I9-H9)/H9,0) -> 0.26187445 | L9: =IF(J9>0,"Over Budget",IF(J9<0,"Under Budget","On Budget")) -> Over Budget
A10: 8 | B10: 2024-01-01 | C10: Jan | D10: Q1 | E10: Training | F10: IT | G10: Certifications | H10: 1045.7 | I10: 923.7 | J10: =I10-H10 -> -122 | K10: =IFERROR((I10-H10)/H10,0) -> -0.11666826 | L10: =IF(J10>0,"Over Budget",IF(J10<0,"Under Budget","On Budget")) -> Under Budget
A11: 9 | B11: 2024-01-01 | C11: Jan | D11: Q1 | E11: Miscellaneous | F11: HR | G11: Bank charges | H11: 315.61 | I11: 284.76 | J11: =I11-H11 -> -30.85 | K11: =IFERROR((I11-H11)/H11,0) -> -0.09774722 | L11: =IF(J11>0,"Over Budget",IF(J11<0,"Under Budget","On Budget")) -> Under Budget
A12: 10 | B12: 2024-02-01 | C12: Feb | D12: Q1 | E12: Salaries | F12: Finance | G12: Bonus payment | H12: 9961.44 | I12: 12106.3 | J12: =I12-H12 -> 2144.86 | K12: =IFERROR((I12-H12)/H12,0) -> 0.21531626 | L12: =IF(J12>0,"Over Budget",IF(J12<0,"Under Budget","On Budget")) -> Over Budget
A13: 11 | B13: 2024-02-01 | C13: Feb | D13: Q1 | E13: Rent & Utilities | F13: Finance | G13: Office rent | H13: 4355.32 | I13: 3690.82 | J13: =I13-H13 -> -664.5 | K13: =IFERROR((I13-H13)/H13,0) -> -0.15257203 | L13: =IF(J13>0,"Over Budget",IF(J13<0,"Under Budget","On Budget")) -> Under Budget
A14: 12 | B14: 2024-02-01 | C14: Feb | D14: Q1 | E14: IT & Software | F14: HR | G14: IT support | H14: 3118.45 | I14: 3551.35 | J14: =I14-H14 -> 432.9 | K14: =IFERROR((I14-H14)/H14,0) -> 0.13881896 | L14: =IF(J14>0,"Over Budget",IF(J14<0,"Under Budget","On Budget")) -> Over Budget
... A110: 108 | B110: 2024-12-01 | C110: Dec | D110: Q4 | E110: Miscellaneous | F110: Finance | G110: Postage | H110: 174.17 | I110: 199.56 | J110: =I110-H110 -> 25.39 | K110: =IFERROR((I110-H110)/H110,0) -> 0.14577711 | L110: =IF(J110>0,"Over Budget",IF(J110<0,"Under Budget","On Budget")) -> Over Budget

Sheet Dashboard
A1: SME Expense Tracker | Financial Dashboard | FY 2024
A2: All figures in GBP (£) | Data source: Expense Data sheet | Refresh: Open workbook
A4: TOTAL BUDGET | H4: TOTAL ACTUAL SPEND | O4: TOTAL VARIANCE | V4: OVER-BUDGET ITEMS | AC4: UNDER-BUDGET ITEMS
A6: =SUMIF('Expense Data'!E:E,"<>",'Expense Data'!H:H) -> 334609.55 | H6: =SUMIF('Expense Data'!E:E,"<>",'Expense Data'!I:I) -> 331271.77 | O6: =SUMIF('Expense Data'!E:E,"<>",'Expense Data'!J:J) -> -3337.78 | V6: =COUNTIF('Expense Data'!L:L,"Over Budget") -> 33 | AC6: =COUNTIF('Expense Data'!L:L,"Under Budget") -> 75
A10: ▌ Spend by Category | Q10: ▌ Monthly Spend Trend
A11: Category | G11: Budget £ | L11: Actual £ | Q11: Variance £ | V11: Var % | AA11: Status
A12: Salaries | G12: =SUMIF('Expense Data'!E:E,"Salaries",'Expense Data'!H:H) -> 136016.54 | L12: =SUMIF('Expense Data'!E:E,"Salaries",'Expense Data'!I:I) -> 144250.53 | Q12: =H12-G12 -> -136016.54 | V12: =IFERROR(I12/G12-1,0) -> -1 | AA12: =IF(I12>0,"▲ Over","▼ Under") -> ▼ Under
A13: Rent & Utilities | G13: =SUMIF('Expense Data'!E:E,"Rent & Utilities",'Expense Data'!H:H) -> 49883.81 | L13: =SUMIF('Expense Data'!E:E,"Rent & Utilities",'Expense Data'!I:I) -> 49944.7 | Q13: =H13-G13 -> -49883.81 | V13: =IFERROR(I13/G13-1,0) -> -1 | AA13: =IF(I13>0,"▲ Over","▼ Under") -> ▼ Under
A14: IT & Software | G14: =SUMIF('Expense Data'!E:E,"IT & Software",'Expense Data'!H:H) -> 26805.54 | L14: =SUMIF('Expense Data'!E:E,"IT & Software",'Expense Data'!I:I) -> 26387.88 | Q14: =H14-G14 -> -26805.54 | V14: =IFERROR(I14/G14-1,0) -> -1 | AA14: =IF(I14>0,"▲ Over","▼ Under") -> ▼ Under
A15: Marketing | G15: =SUMIF('Expense Data'!E:E,"Marketing",'Expense Data'!H:H) -> 47561.04 | L15: =SUMIF('Expense Data'!E:E,"Marketing",'Expense Data'!I:I) -> 41721.28 | Q15: =H15-G15 -> -47561.04 | V15: =IFERROR(I15/G15-1,0) -> -1 | AA15: =IF(I15>0,"▲ Over","▼ Under") -> ▼ Under
A16: Travel | G16: =SUMIF('Expense Data'!E:E,"Travel",'Expense Data'!H:H) -> 14881.17 | L16: =SUMIF('Expense Data'!E:E,"Travel",'Expense Data'!I:I) -> 13375.02 | Q16: =H16-G16 -> -14881.17 | V16: =IFERROR(I16/G16-1,0) -> -1 | AA16: =IF(I16>0,"▲ Over","▼ Under") -> ▼ Under
A17: Office Supplies | G17: =SUMIF('Expense Data'!E:E,"Office Supplies",'Expense Data'!H:H) -> 6945.68 | L17: =SUMIF('Expense Data'!E:E,"Office Supplies",'Expense Data'!I:I) -> 7323.2 | Q17: =H17-G17 -> -6945.68 | V17: =IFERROR(I17/G17-1,0) -> -1 | AA17: =IF(I17>0,"▲ Over","▼ Under") -> ▼ Under
A18: Professional Services | G18: =SUMIF('Expense Data'!E:E,"Professional Services",'Expense Data'!H:H) -> 39354.37 | L18: =SUMIF('Expense Data'!E:E,"Professional Services",'Expense Data'!I:I) -> 36215.68 | Q18: =H18-G18 -> -39354.37 | V18: =IFERROR(I18/G18-1,0) -> -1 | AA18: =IF(I18>0,"▲ Over","▼ Under") -> ▼ Under
A19: Training | G19: =SUMIF('Expense Data'!E:E,"Training",'Expense Data'!H:H) -> 9689.47 | L19: =SUMIF('Expense Data'!E:E,"Training",'Expense Data'!I:I) -> 8773.6 | Q19: =H19-G19 -> -9689.47 | V19: =IFERROR(I19/G19-1,0) -> -1 | AA19: =IF(I19>0,"▲ Over","▼ Under") -> ▼ Under
A20: Miscellaneous | G20: =SUMIF('Expense Data'!E:E,"Miscellaneous",'Expense Data'!H:H) -> 3471.93 | L20: =SUMIF('Expense Data'!E:E,"Miscellaneous",'Expense Data'!I:I) -> 3279.88 | Q20: =H20-G20 -> -3471.93 | V20: =IFERROR(I20/G20-1,0) -> -1 | AA20: =IF(I20>0,"▲ Over","▼ Under") -> ▼ Under
A21: TOTAL | G21: =SUM(G12:G20) -> 334609.55 | L21: =SUM(H12:H20) -> 0 | Q21: =SUM(I12:I20) -> 0 | V21: =IFERROR(H21/G21-1,0) -> -1
S34: Month | T34: Budget £ | U34: Actual £
S35: Jan | T35: =SUMIFS('Expense Data'!H:H,'Expense Data'!C:C,"Jan") -> 22825.81 | U35: =SUMIFS('Expense Data'!I:I,'Expense Data'!C:C,"Jan") -> 22859.04
S36: Feb | T36: =SUMIFS('Expense Data'!H:H,'Expense Data'!C:C,"Feb") -> 29290.46 | U36: =SUMIFS('Expense Data'!I:I,'Expense Data'!C:C,"Feb") -> 29746.87
S37: Mar | T37: =SUMIFS('Expense Data'!H:H,'Expense Data'!C:C,"Mar") -> 25055.76 | U37: =SUMIFS('Expense Data'!I:I,'Expense Data'!C:C,"Mar") -> 22388.18
S38: Apr | T38: =SUMIFS('Expense Data'!H:H,'Expense Data'!C:C,"Apr") -> 33062.11 | U38: =SUMIFS('Expense Data'!I:I,'Expense Data'!C:C,"Apr") -> 33017.18
S39: May | T39: =SUMIFS('Expense Data'!H:H,'Expense Data'!C:C,"May") -> 24132.53 | U39: =SUMIFS('Expense Data'!I:I,'Expense Data'!C:C,"May") -> 22121.62
S40: Jun | T40: =SUMIFS('Expense Data'!H:H,'Expense Data'!C:C,"Jun") -> 27909.44 | U40: =SUMIFS('Expense Data'!I:I,'Expense Data'!C:C,"Jun") -> 26309.05
S41: Jul | T41: =SUMIFS('Expense Data'!H:H,'Expense Data'!C:C,"Jul") -> 27350.85 | U41: =SUMIFS('Expense Data'!I:I,'Expense Data'!C:C,"Jul") -> 27450.03
S42: Aug | T42: =SUMIFS('Expense Data'!H:H,'Expense Data'!C:C,"Aug") -> 29181.92 | U42: =SUMIFS('Expense Data'!I:I,'Expense Data'!C:C,"Aug") -> 29119.51
S43: Sep | T43: =SUMIFS('Expense Data'!H:H,'Expense Data'!C:C,"Sep") -> 28415.52 | U43: =SUMIFS('Expense Data'!I:I,'Expense Data'!C:C,"Sep") -> 28551.5
S44: Oct | T44: =SUMIFS('Expense Data'!H:H,'Expense Data'!C:C,"Oct") -> 30191.8 | U44: =SUMIFS('Expense Data'!I:I,'Expense Data'!C:C,"Oct") -> 32776.96
S45: Nov | T45: =SUMIFS('Expense Data'!H:H,'Expense Data'!C:C,"Nov") -> 29124.51 | U45: =SUMIFS('Expense Data'!I:I,'Expense Data'!C:C,"Nov") -> 27019.21
S46: Dec | T46: =SUMIFS('Expense Data'!H:H,'Expense Data'!C:C,"Dec") -> 28068.84 | U46: =SUMIFS('Expense Data'!I:I,'Expense Data'!C:C,"Dec") -> 29912.62

Sheet Monthly Summary
A1: Monthly Expense Summary | Actual Spend by Category
A2: Category | B2: Jan | C2: Feb | D2: Mar | E2: Apr | F2: May | G2: Jun | H2: Jul | I2: Aug | J2: Sep | K2: Oct | L2: Nov | M2: Dec | N2: Total
A3: Salaries | B3: =SUMIFS('Expense Data'!I:I,'Expense Data'!E:E,"Salaries",'Expense Data'!C:C,"Jan") -> 10090.5 | C3: =SUMIFS('Expense Data'!I:I,'Expense Data'!E:E,"Salaries",'Expense Data'!C:C,"Feb") -> 12106.3 | D3: =SUMIFS('Expense Data'!I:I,'Expense Data'!E:E,"Salaries",'Expense Data'!C:C,"Mar") -> 8572.82 | E3: =SUMIFS('Expense Data'!I:I,'Expense Data'!E:E,"Salaries",'Expense Data'!C:C,"Apr") -> 14943.17 | F3: =SUMIFS('Expense Data'!I:I,'Expense Data'!E:E,"Salaries",'Expense Data'!C:C,"May") -> 8152.23 | G3: =SUMIFS('Expense Data'!I:I,'Expense Data'!E:E,"Salaries",'Expense Data'!C:C,"Jun") -> 9943.51 | H3: =SUMIFS('Expense Data'!I:I,'Expense Data'!E:E,"Salaries",'Expense Data'!C:C,"Jul") -> 9818.1 | I3: =SUMIFS('Expense Data'!I:I,'Expense Data'!E:E,"Salaries",'Expense Data'!C:C,"Aug") -> 14774.57 | J3: =SUMIFS('Expense Data'!I:I,'Expense Data'!E:E,"Salaries",'Expense Data'!C:C,"Sep") -> 10811.18 | K3: =SUMIFS('Expense Data'!I:I,'Expense Data'!E:E,"Salaries",'Expense Data'!C:C,"Oct") -> 17703.7 | L3: =SUMIFS('Expense Data'!I:I,'Expense Data'!E:E,"Salaries",'Expense Data'!C:C,"Nov") -> 11206.08 | M3: =SUMIFS('Expense Data'!I:I,'Expense Data'!E:E,"Salaries",'Expense Data'!C:C,"Dec") -> 16128.37 | N3: =SUM(B3:M3) -> 144250.53
A4: Rent & Utilities | B4: =SUMIFS('Expense Data'!I:I,'Expense Data'!E:E,"Rent & Utilities",'Expense Data'!C:C,"Jan") -> 3257.81 | C4: =SUMIFS('Expense Data'!I:I,'Expense Data'!E:E,"Rent & Utilities",'Expense Data'!C:C,"Feb") -> 3690.82 | D4: =SUMIFS('Expense Data'!I:I,'Expense Data'!E:E,"Rent & Utilities",'Expense Data'!C:C,"Mar") -> 3312.68 | E4: =SUMIFS('Expense Data'!I:I,'Expense Data'!E:E,"Rent & Utilities",'Expense Data'!C:C,"Apr") -> 3854.6 | F4: =SUMIFS('Expense Data'!I:I,'Expense Data'!E:E,"Rent & Utilities",'Expense Data'!C:C,"May") -> 4489.13 | G4: =SUMIFS('Expense Data'!I:I,'Expense Data'!E:E,"Rent & Utilities",'Expense Data'!C:C,"Jun") -> 4422.2 | H4: =SUMIFS('Expense Data'!I:I,'Expense Data'!E:E,"Rent & Utilities",'Expense Data'!C:C,"Jul") -> 4298.46 | I4: =SUMIFS('Expense Data'!I:I,'Expense Data'!E:E,"Rent & Utilities",'Expense Data'!C:C,"Aug") -> 4868.76 | J4: =SUMIFS('Expense Data'!I:I,'Expense Data'!E:E,"Rent & Utilities",'Expense Data'!C:C,"Sep") -> 4352.71 | K4: =SUMIFS('Expense Data'!I:I,'Expense Data'!E:E,"Rent & Utilities",'Expense Data'!C:C,"Oct") -> 4806.59 | L4: =SUMIFS('Expense Data'!I:I,'Expense Data'!E:E,"Rent & Utilities",'Expense Data'!C:C,"Nov") -> 4741.29 | M4: =SUMIFS('Expense Data'!I:I,'Expense Data'!E:E,"Rent & Utilities",'Expense Data'!C:C,"Dec") -> 3849.65 | N4: =SUM(B4:M4) -> 49944.7
A5: IT & Software | B5: =SUMIFS('Expense Data'!I:I,'Expense Data'!E:E,"IT & Software",'Expense Data'!C:C,"Jan") -> 1492.22 | C5: =SUMIFS('Expense Data'!I:I,'Expense Data'!E:E,"IT & Software",'Expense Data'!C:C,"Feb") -> 3551.35 | D5: =SUMIFS('Expense Data'!I:I,'Expense Data'!E:E,"IT & Software",'Expense Data'!C:C,"Mar") -> 2237.14 | E5: =SUMIFS('Expense Data'!I:I,'Expense Data'!E:E,"IT & Software",'Expense Data'!C:C,"Apr") -> 2675.83 | F5: =SUMIFS('Expense Data'!I:I,'Expense Data'!E:E,"IT & Software",'Expense Data'!C:C,"May") -> 1659.07 | G5: =SUMIFS('Expense Data'!I:I,'Expense Data'!E:E,"IT & Software",'Expense Data'!C:C,"Jun") -> 2046.95 | H5: =SUMIFS('Expense Data'!I:I,'Expense Data'!E:E,"IT & Software",'Expense Data'!C:C,"Jul") -> 2346.78 | I5: =SUMIFS('Expense Data'!I:I,'Expense Data'!E:E,"IT & Software",'Expense Data'!C:C,"Aug") -> 1369.18 | J5: =SUMIFS('Expense Data'!I:I,'Expense Data'!E:E,"IT & Software",'Expense Data'!C:C,"Sep") -> 3316.85 | K5: =SUMIFS('Expense Data'!I:I,'Expense Data'!E:E,"IT & Software",'Expense Data'!C:C,"Oct") -> 2586.44 | L5: =SUMIFS('Expense Data'!I:I,'Expense Data'!E:E,"IT & Software",'Expense Data'!C:C,"Nov") -> 1776.94 | M5: =SUMIFS('Expense Data'!I:I,'Expense Data'!E:E,"IT & Software",'Expense Data'!C:C,"Dec") -> 1329.13 | N5: =SUM(B5:M5) -> 26387.88
A6: Marketing | B6: =SUMIFS('Expense Data'!I:I,'Expense Data'!E:E,"Marketing",'Expense Data'!C:C,"Jan") -> 2741.45 | C6: =SUMIFS('Expense Data'!I:I,'Expense Data'!E:E,"Marketing",'Expense Data'!C:C,"Feb") -> 3575.78 | D6: =SUMIFS('Expense Data'!I:I,'Expense Data'!E:E,"Marketing",'Expense Data'!C:C,"Mar") -> 2673.53 | E6: =SUMIFS('Expense Data'!I:I,'Expense Data'!E:E,"Marketing",'Expense Data'!C:C,"Apr") -> 4003 | F6: =SUMIFS('Expense Data'!I:I,'Expense Data'!E:E,"Marketing",'Expense Data'!C:C,"May") -> 2582.16 | G6: =SUMIFS('Expense Data'!I:I,'Expense Data'!E:E,"Marketing",'Expense Data'!C:C,"Jun") -> 2985.9 | H6: =SUMIFS('Expense Data'!I:I,'Expense Data'!E:E,"Marketing",'Expense Data'!C:C,"Jul") -> 3993.71 | I6: =SUMIFS('Expense Data'!I:I,'Expense Data'!E:E,"Marketing",'Expense Data'!C:C,"Aug") -> 4074.9 | J6: =SUMIFS('Expense Data'!I:I,'Expense Data'!E:E,"Marketing",'Expense Data'!C:C,"Sep") -> 4587.65 | K6: =SUMIFS('Expense Data'!I:I,'Expense Data'!E:E,"Marketing",'Expense Data'!C:C,"Oct") -> 2992.42 | L6: =SUMIFS('Expense Data'!I:I,'Expense Data'!E:E,"Marketing",'Expense Data'!C:C,"Nov") -> 4535.97 | M6: =SUMIFS('Expense Data'!I:I,'Expense Data'!E:E,"Marketing",'Expense Data'!C:C,"Dec") -> 2974.81 | N6: =SUM(B6:M6) -> 41721.28
A7: Travel | B7: =SUMIFS('Expense Data'!I:I,'Expense Data'!E:E,"Travel",'Expense Data'!C:C,"Jan") -> 995.36 | C7: =SUMIFS('Expense Data'!I:I,'Expense Data'!E:E,"Travel",'Expense Data'!C:C,"Feb") -> 1446.43 | D7: =SUMIFS('Expense Data'!I:I,'Expense Data'!E:E,"Travel",'Expense Data'!C:C,"Mar") -> 1075.5 | E7: =SUMIFS('Expense Data'!I:I,'Expense Data'!E:E,"Travel",'Expense Data'!C:C,"Apr") -> 1399.22 | F7: =SUMIFS('Expense Data'!I:I,'Expense Data'!E:E,"Travel",'Expense Data'!C:C,"May") -> 1239.08 | G7: =SUMIFS('Expense Data'!I:I,'Expense Data'!E:E,"Travel",'Expense Data'!C:C,"Jun") -> 1095.37 | H7: =SUMIFS('Expense Data'!I:I,'Expense Data'!E:E,"Travel",'Expense Data'!C:C,"Jul") -> 1306.94 | I7: =SUMIFS('Expense Data'!I:I,'Expense Data'!E:E,"Travel",'Expense Data'!C:C,"Aug") -> 515.85 | J7: =SUMIFS('Expense Data'!I:I,'Expense Data'!E:E,"Travel",'Expense Data'!C:C,"Sep") -> 1961.16 | K7: =SUMIFS('Expense Data'!I:I,'Expense Data'!E:E,"Travel",'Expense Data'!C:C,"Oct") -> 532.1 | L7: =SUMIFS('Expense Data'!I:I,'Expense Data'!E:E,"Travel",'Expense Data'!C:C,"Nov") -> 848.77 | M7: =SUMIFS('Expense Data'!I:I,'Expense Data'!E:E,"Travel",'Expense Data'!C:C,"Dec") -> 959.24 | N7: =SUM(B7:M7) -> 13375.02
A8: Office Supplies | B8: =SUMIFS('Expense Data'!I:I,'Expense Data'!E:E,"Office Supplies",'Expense Data'!C:C,"Jan") -> 485.88 | C8: =SUMIFS('Expense Data'!I:I,'Expense Data'!E:E,"Office Supplies",'Expense Data'!C:C,"Feb") -> 633.03 | D8: =SUMIFS('Expense Data'!I:I,'Expense Data'!E:E,"Office Supplies",'Expense Data'!C:C,"Mar") -> 706.95 | E8: =SUMIFS('Expense Data'!I:I,'Expense Data'!E:E,"Office Supplies",'Expense Data'!C:C,"Apr") -> 799.07 | F8: =SUMIFS('Expense Data'!I:I,'Expense Data'!E:E,"Office Supplies",'Expense Data'!C:C,"May") -> 385.11 | G8: =SUMIFS('Expense Data'!I:I,'Expense Data'!E:E,"Office Supplies",'Expense Data'!C:C,"Jun") -> 644.47 | H8: =SUMIFS('Expense Data'!I:I,'Expense Data'!E:E,"Office Supplies",'Expense Data'!C:C,"Jul") -> 770.36 | I8: =SUMIFS('Expense Data'!I:I,'Expense Data'!E:E,"Office Supplies",'Expense Data'!C:C,"Aug") -> 500.9 | J8: =SUMIFS('Expense Data'!I:I,'Expense Data'!E:E,"Office Supplies",'Expense Data'!C:C,"Sep") -> 521.15 | K8: =SUMIFS('Expense Data'!I:I,'Expense Data'!E:E,"Office Supplies",'Expense Data'!C:C,"Oct") -> 673.47 | L8: =SUMIFS('Expense Data'!I:I,'Expense Data'!E:E,"Office Supplies",'Expense Data'!C:C,"Nov") -> 607.92 | M8: =SUMIFS('Expense Data'!I:I,'Expense Data'!E:E,"Office Supplies",'Expense Data'!C:C,"Dec") -> 594.89 | N8: =SUM(B8:M8) -> 7323.2
A9: Professional Services | B9: =SUMIFS('Expense Data'!I:I,'Expense Data'!E:E,"Professional Services",'Expense Data'!C:C,"Jan") -> 2587.36 | C9: =SUMIFS('Expense Data'!I:I,'Expense Data'!E:E,"Professional Services",'Expense Data'!C:C,"Feb") -> 3425.15 | D9: =SUMIFS('Expense Data'!I:I,'Expense Data'!E:E,"Professional Services",'Expense Data'!C:C,"Mar") -> 2164.93 | E9: =SUMIFS('Expense Data'!I:I,'Expense Data'!E:E,"Professional Services",'Expense Data'!C:C,"Apr") -> 4111.86 | F9: =SUMIFS('Expense Data'!I:I,'Expense Data'!E:E,"Professional Services",'Expense Data'!C:C,"May") -> 2831.64 | G9: =SUMIFS('Expense Data'!I:I,'Expense Data'!E:E,"Professional Services",'Expense Data'!C:C,"Jun") -> 4272.68 | H9: =SUMIFS('Expense Data'!I:I,'Expense Data'!E:E,"Professional Services",'Expense Data'!C:C,"Jul") -> 4156.65 | I9: =SUMIFS('Expense Data'!I:I,'Expense Data'!E:E,"Professional Services",'Expense Data'!C:C,"Aug") -> 1938.87 | J9: =SUMIFS('Expense Data'!I:I,'Expense Data'!E:E,"Professional Services",'Expense Data'!C:C,"Sep") -> 2131.61 | K9: =SUMIFS('Expense Data'!I:I,'Expense Data'!E:E,"Professional Services",'Expense Data'!C:C,"Oct") -> 2746.54 | L9: =SUMIFS('Expense Data'!I:I,'Expense Data'!E:E,"Professional Services",'Expense Data'!C:C,"Nov") -> 2351.4 | M9: =SUMIFS('Expense Data'!I:I,'Expense Data'!E:E,"Professional Services",'Expense Data'!C:C,"Dec") -> 3496.99 | N9: =SUM(B9:M9) -> 36215.68
A10: Training | B10: =SUMIFS('Expense Data'!I:I,'Expense Data'!E:E,"Training",'Expense Data'!C:C,"Jan") -> 923.7 | C10: =SUMIFS('Expense Data'!I:I,'Expense Data'!E:E,"Training",'Expense Data'!C:C,"Feb") -> 1045.86 | D10: =SUMIFS('Expense Data'!I:I,'Expense Data'!E:E,"Training",'Expense Data'!C:C,"Mar") -> 1293.46 | E10: =SUMIFS('Expense Data'!I:I,'Expense Data'!E:E,"Training",'Expense Data'!C:C,"Apr") -> 887.38 | F10: =SUMIFS('Expense Data'!I:I,'Expense Data'!E:E,"Training",'Expense Data'!C:C,"May") -> 548.69 | G10: =SUMIFS('Expense Data'!I:I,'Expense Data'!E:E,"Training",'Expense Data'!C:C,"Jun") -> 689.35 | H10: =SUMIFS('Expense Data'!I:I,'Expense Data'!E:E,"Training",'Expense Data'!C:C,"Jul") -> 485.06 | I10: =SUMIFS('Expense Data'!I:I,'Expense Data'!E:E,"Training",'Expense Data'!C:C,"Aug") -> 847.8 | J10: =SUMIFS('Expense Data'!I:I,'Expense Data'!E:E,"Training",'Expense Data'!C:C,"Sep") -> 531.66 | K10: =SUMIFS('Expense Data'!I:I,'Expense Data'!E:E,"Training",'Expense Data'!C:C,"Oct") -> 551.97 | L10: =SUMIFS('Expense Data'!I:I,'Expense Data'!E:E,"Training",'Expense Data'!C:C,"Nov") -> 588.69 | M10: =SUMIFS('Expense Data'!I:I,'Expense Data'!E:E,"Training",'Expense Data'!C:C,"Dec") -> 379.98 | N10: =SUM(B10:M10) -> 8773.6
A11: Miscellaneous | B11: =SUMIFS('Expense Data'!I:I,'Expense Data'!E:E,"Miscellaneous",'Expense Data'!C:C,"Jan") -> 284.76 | C11: =SUMIFS('Expense Data'!I:I,'Expense Data'!E:E,"Miscellaneous",'Expense Data'!C:C,"Feb") -> 272.15 | D11: =SUMIFS('Expense Data'!I:I,'Expense Data'!E:E,"Miscellaneous",'Expense Data'!C:C,"Mar") -> 351.17 | E11: =SUMIFS('Expense Data'!I:I,'Expense Data'!E:E,"Miscellaneous",'Expense Data'!C:C,"Apr") -> 343.05 | F11: =SUMIFS('Expense Data'!I:I,'Expense Data'!E:E,"Miscellaneous",'Expense Data'!C:C,"May") -> 234.51 | G11: =SUMIFS('Expense Data'!I:I,'Expense Data'!E:E,"Miscellaneous",'Expense Data'!C:C,"Jun") -> 208.62 | H11: =SUMIFS('Expense Data'!I:I,'Expense Data'!E:E,"Miscellaneous",'Expense Data'!C:C,"Jul") -> 273.97 | I11: =SUMIFS('Expense Data'!I:I,'Expense Data'!E:E,"Miscellaneous",'Expense Data'!C:C,"Aug") -> 228.68 | J11: =SUMIFS('Expense Data'!I:I,'Expense Data'!E:E,"Miscellaneous",'Expense Data'!C:C,"Sep") -> 337.53 | K11: =SUMIFS('Expense Data'!I:I,'Expense Data'!E:E,"Miscellaneous",'Expense Data'!C:C,"Oct") -> 183.73 | L11: =SUMIFS('Expense Data'!I:I,'Expense Data'!E:E,"Miscellaneous",'Expense Data'!C:C,"Nov") -> 362.15 | M11: =SUMIFS('Expense Data'!I:I,'Expense Data'!E:E,"Miscellaneous",'Expense Data'!C:C,"Dec") -> 199.56 | N11: =SUM(B11:M11) -> 3279.88
A12: GRAND TOTAL | B12: =SUM(B3:B11) -> 22859.04 | C12: =SUM(C3:C11) -> 29746.87 | D12: =SUM(D3:D11) -> 22388.18 | E12: =SUM(E3:E11) -> 33017.18 | F12: =SUM(F3:F11) -> 22121.62 | G12: =SUM(G3:G11) -> 26309.05 | H12: =SUM(H3:H11) -> 27450.03 | I12: =SUM(I3:I11) -> 29119.51 | ... N12: =SUM(N3:N11) -> 331271.77

Sheet KPI Summary
A1: KPI Summary | Budget vs Actual Performance
A2: Metric | B2: Q1 | C2: Q2 | D2: Q3 | E2: Q4 | F2: Full Year | G2: vs Budget | H2: Status
A3: Total Budget (£) | B3: =SUMIFS('Expense Data'!H:H,'Expense Data'!D:D,"Q1") -> 77172.03 | C3: =SUMIFS('Expense Data'!H:H,'Expense Data'!D:D,"Q2") -> 85104.08 | D3: =SUMIFS('Expense Data'!H:H,'Expense Data'!D:D,"Q3") -> 84948.29 | E3: =SUMIFS('Expense Data'!H:H,'Expense Data'!D:D,"Q4") -> 87385.15 | F3: =SUM(B3:E3) -> 334609.55 | G3: "" | H3: "Target"
A4: Total Actual (£) | B4: =SUMIFS('Expense Data'!I:I,'Expense Data'!D:D,"Q1") -> 74994.09 | C4: =SUMIFS('Expense Data'!I:I,'Expense Data'!D:D,"Q2") -> 81447.85 | D4: =SUMIFS('Expense Data'!I:I,'Expense Data'!D:D,"Q3") -> 85121.04 | E4: =SUMIFS('Expense Data'!I:I,'Expense Data'!D:D,"Q4") -> 89708.79 | F4: =SUM(B4:E4) -> 331271.77 | G4: "" | H4: "Actual"
A5: Variance (£) | B5: =B4-B3 -> -2177.94 | C5: =C4-C3 -> -3656.23 | D5: =D4-D3 -> 172.75 | E5: =E4-E3 -> 2323.64 | F5: =F4-F3 -> -3337.78 | G5: =IFERROR(F4/F3-1,0) -> -0.0099751486 | H5: =IF(G5>0,"Over Budget","Under Budget") -> Under Budget
A6: Over-Budget Items | B6: =COUNTIFS('Expense Data'!D:D,"Q1",'Expense Data'!L:L,"Over Budget") -> 10 | C6: =COUNTIFS('Expense Data'!D:D,"Q2",'Expense Data'!L:L,"Over Budget") -> 7 | D6: =COUNTIFS('Expense Data'!D:D,"Q3",'Expense Data'!L:L,"Over Budget") -> 8 | E6: =COUNTIFS('Expense Data'!D:D,"Q4",'Expense Data'!L:L,"Over Budget") -> 8 | F6: =SUM(B6:E6) -> 33 | G6: "" | H6: ""
A7: Under-Budget Items | B7: =COUNTIFS('Expense Data'!D:D,"Q1",'Expense Data'!L:L,"Under Budget") -> 17 | C7: =COUNTIFS('Expense Data'!D:D,"Q2",'Expense Data'!L:L,"Under Budget") -> 20 | D7: =COUNTIFS('Expense Data'!D:D,"Q3",'Expense Data'!L:L,"Under Budget") -> 19 | E7: =COUNTIFS('Expense Data'!D:D,"Q4",'Expense Data'!L:L,"Under Budget") -> 19 | F7: =SUM(B7:E7) -> 75 | G7: "" | H7: ""
