Workbook

Sheet Expense Data
A1: # | B1: Date | C1: Month | D1: Quarter | E1: Category | F1: Department | G1: Description | H1: Budget (£) | I1: Actual (£) | J1: Variance (£) | K1: Variance % | L1: Status
A2: 1 | B2: 2024-01-01 | C2: Jan | D2: Q1 | E2: Rent & Utilities | F2: Marketing | G2: Internet & phones | H2: 3440.88 | I2: 3249.1 | J2: =I2-H2 -> -191.78 | K2: =IFERROR((I2-H2)/H2,0) -> -0.055735742 | L2: =IF(J2>0,"Over Budget",IF(J2<0,"Under Budget","On Budget")) -> Under Budget
A3: 2 | B3: 2024-01-01 | C3: Jan | D3: Q1 | E3: Professional Services | F3: Operations | G3: Accounting fees | H3: 3943.49 | I3: 3104.77 | J3: =I3-H3 -> -838.72 | K3: =IFERROR((I3-H3)/H3,0) -> -0.2126847 | L3: =IF(J3>0,"Over Budget",IF(J3<0,"Under Budget","On Budget")) -> Under Budget
A4: 3 | B4: 2024-01-01 | C4: Jan | D4: Q1 | E4: IT & Software | F4: Finance | G4: SaaS subscriptions | H4: 1278.24 | I4: 1667.14 | J4: =I4-H4 -> 388.9 | K4: =IFERROR((I4-H4)/H4,0) -> 0.30424646 | L4: =IF(J4>0,"Over Budget",IF(J4<0,"Under Budget","On Budget")) -> Over Budget
A5: 4 | B5: 2024-01-01 | C5: Jan | D5: Q1 | E5: Rent & Utilities | F5: IT | G5: Water rates | H5: 4614.26 | I5: 4054.53 | J5: =I5-H5 -> -559.73 | K5: =IFERROR((I5-H5)/H5,0) -> -0.12130439 | L5: =IF(J5>0,"Over Budget",IF(J5<0,"Under Budget","On Budget")) -> Under Budget
A6: 5 | B6: 2024-01-01 | C6: Jan | D6: Q1 | E6: Salaries | F6: HR | G6: Monthly payroll | H6: 11864.28 | I6: 10659.4 | J6: =I6-H6 -> -1204.88 | K6: =IFERROR((I6-H6)/H6,0) -> -0.10155526 | L6: =IF(J6>0,"Over Budget",IF(J6<0,"Under Budget","On Budget")) -> Under Budget
A7: 6 | B7: 2024-01-01 | C7: Jan | D7: Q1 | E7: Professional Services | F7: Finance | G7: Accounting fees | H7: 3966 | I7: 4435.45 | J7: =I7-H7 -> 469.45 | K7: =IFERROR((I7-H7)/H7,0) -> 0.11836863 | L7: =IF(J7>0,"Over Budget",IF(J7<0,"Under Budget","On Budget")) -> Over Budget
A8: 7 | B8: 2024-01-01 | C8: Jan | D8: Q1 | E8: Travel & Expenses | F8: Finance | G8: Client visit flights | H8: 1782.98 | I8: 1499.9 | J8: =I8-H8 -> -283.08 | K8: =IFERROR((I8-H8)/H8,0) -> -0.15876791 | L8: =IF(J8>0,"Over Budget",IF(J8<0,"Under Budget","On Budget")) -> Under Budget
A9: 8 | B9: 2024-01-01 | C9: Jan | D9: Q1 | E9: Office Supplies | F9: HR | G9: Coffee & refreshments | H9: 297.59 | I9: 271.06 | J9: =I9-H9 -> -26.53 | K9: =IFERROR((I9-H9)/H9,0) -> -0.089149501 | L9: =IF(J9>0,"Over Budget",IF(J9<0,"Under Budget","On Budget")) -> Under Budget
A10: 9 | B10: 2024-01-01 | C10: Jan | D10: Q1 | E10: Salaries | F10: Marketing | G10: Monthly payroll | H10: 12263.92 | I10: 15559.7 | J10: =I10-H10 -> 3295.78 | K10: =IFERROR((I10-H10)/H10,0) -> 0.26873789 | L10: =IF(J10>0,"Over Budget",IF(J10<0,"Under Budget","On Budget")) -> Over Budget
A11: 10 | B11: 2024-01-01 | C11: Jan | D11: Q1 | E11: Salaries | F11: Sales | G11: Overtime pay | H11: 10656.19 | I11: 9628.93 | J11: =I11-H11 -> -1027.26 | K11: =IFERROR((I11-H11)/H11,0) -> -0.096400308 | L11: =IF(J11>0,"Over Budget",IF(J11<0,"Under Budget","On Budget")) -> Under Budget
A12: 11 | B12: 2024-01-01 | C12: Jan | D12: Q1 | E12: IT & Software | F12: IT | G12: Hardware purchase | H12: 3053.84 | I12: 2859.13 | J12: =I12-H12 -> -194.71 | K12: =IFERROR((I12-H12)/H12,0) -> -0.063759071 | L12: =IF(J12>0,"Over Budget",IF(J12<0,"Under Budget","On Budget")) -> Under Budget
A13: 12 | B13: 2024-01-01 | C13: Jan | D13: Q1 | E13: Office Supplies | F13: Sales | G13: Stationery | H13: 683.03 | I13: 523.12 | J13: =I13-H13 -> -159.91 | K13: =IFERROR((I13-H13)/H13,0) -> -0.23411856 | L13: =IF(J13>0,"Over Budget",IF(J13<0,"Under Budget","On Budget")) -> Under Budget
... A131: 130 | B131: 2024-12-01 | C131: Dec | D131: Q4 | E131: IT & Software | F131: HR | G131: SaaS subscriptions | H131: 2972.98 | I131: 2524.59 | J131: =I131-H131 -> -448.39 | K131: =IFERROR((I131-H131)/H131,0) -> -0.15082173 | L131: =IF(J131>0,"Over Budget",IF(J131<0,"Under Budget","On Budget")) -> Under Budget

Sheet Monthly Summary
A1: SME Expense Tracker — Monthly Summary 2024
A2: Category | B2: Jan | C2: Feb | D2: Mar | E2: Apr | F2: May | G2: Jun | H2: Jul | I2: Aug | J2: Sep | K2: Oct | L2: Nov | M2: Dec | N2: Total
A3: Salaries | B3: =SUMIFS('Expense Data'!I:I,'Expense Data'!E:E,A3,'Expense Data'!C:C,"Jan") -> 35848.03 | C3: =SUMIFS('Expense Data'!I:I,'Expense Data'!E:E,A3,'Expense Data'!C:C,"Feb") -> 25573.77 | D3: =SUMIFS('Expense Data'!I:I,'Expense Data'!E:E,A3,'Expense Data'!C:C,"Mar") -> 14098.33 | E3: =SUMIFS('Expense Data'!I:I,'Expense Data'!E:E,A3,'Expense Data'!C:C,"Apr") -> 16217.24 | F3: =SUMIFS('Expense Data'!I:I,'Expense Data'!E:E,A3,'Expense Data'!C:C,"May") -> 11138.98 | G3: =SUMIFS('Expense Data'!I:I,'Expense Data'!E:E,A3,'Expense Data'!C:C,"Jun") -> 0 | H3: =SUMIFS('Expense Data'!I:I,'Expense Data'!E:E,A3,'Expense Data'!C:C,"Jul") -> 16689.87 | I3: =SUMIFS('Expense Data'!I:I,'Expense Data'!E:E,A3,'Expense Data'!C:C,"Aug") -> 19833.34 | J3: =SUMIFS('Expense Data'!I:I,'Expense Data'!E:E,A3,'Expense Data'!C:C,"Sep") -> 8227.33 | K3: =SUMIFS('Expense Data'!I:I,'Expense Data'!E:E,A3,'Expense Data'!C:C,"Oct") -> 10014.04 | L3: =SUMIFS('Expense Data'!I:I,'Expense Data'!E:E,A3,'Expense Data'!C:C,"Nov") -> 16158.24 | M3: =SUMIFS('Expense Data'!I:I,'Expense Data'!E:E,A3,'Expense Data'!C:C,"Dec") -> 27702.76 | N3: =SUM(B3:M3) -> 201501.93
A4: Rent & Utilities | B4: =SUMIFS('Expense Data'!I:I,'Expense Data'!E:E,A4,'Expense Data'!C:C,"Jan") -> 7303.63 | C4: =SUMIFS('Expense Data'!I:I,'Expense Data'!E:E,A4,'Expense Data'!C:C,"Feb") -> 3045.02 | D4: =SUMIFS('Expense Data'!I:I,'Expense Data'!E:E,A4,'Expense Data'!C:C,"Mar") -> 6525.55 | E4: =SUMIFS('Expense Data'!I:I,'Expense Data'!E:E,A4,'Expense Data'!C:C,"Apr") -> 3251.64 | F4: =SUMIFS('Expense Data'!I:I,'Expense Data'!E:E,A4,'Expense Data'!C:C,"May") -> 9340.37 | G4: =SUMIFS('Expense Data'!I:I,'Expense Data'!E:E,A4,'Expense Data'!C:C,"Jun") -> 7096.01 | H4: =SUMIFS('Expense Data'!I:I,'Expense Data'!E:E,A4,'Expense Data'!C:C,"Jul") -> 3926.19 | I4: =SUMIFS('Expense Data'!I:I,'Expense Data'!E:E,A4,'Expense Data'!C:C,"Aug") -> 4499.54 | J4: =SUMIFS('Expense Data'!I:I,'Expense Data'!E:E,A4,'Expense Data'!C:C,"Sep") -> 0 | K4: =SUMIFS('Expense Data'!I:I,'Expense Data'!E:E,A4,'Expense Data'!C:C,"Oct") -> 4088.43 | L4: =SUMIFS('Expense Data'!I:I,'Expense Data'!E:E,A4,'Expense Data'!C:C,"Nov") -> 0 | M4: =SUMIFS('Expense Data'!I:I,'Expense Data'!E:E,A4,'Expense Data'!C:C,"Dec") -> 3822.21 | N4: =SUM(B4:M4) -> 52898.59
A5: IT & Software | B5: =SUMIFS('Expense Data'!I:I,'Expense Data'!E:E,A5,'Expense Data'!C:C,"Jan") -> 4526.27 | C5: =SUMIFS('Expense Data'!I:I,'Expense Data'!E:E,A5,'Expense Data'!C:C,"Feb") -> 9294.91 | D5: =SUMIFS('Expense Data'!I:I,'Expense Data'!E:E,A5,'Expense Data'!C:C,"Mar") -> 4215.16 | E5: =SUMIFS('Expense Data'!I:I,'Expense Data'!E:E,A5,'Expense Data'!C:C,"Apr") -> 4811.67 | F5: =SUMIFS('Expense Data'!I:I,'Expense Data'!E:E,A5,'Expense Data'!C:C,"May") -> 2888.74 | G5: =SUMIFS('Expense Data'!I:I,'Expense Data'!E:E,A5,'Expense Data'!C:C,"Jun") -> 1434.67 | H5: =SUMIFS('Expense Data'!I:I,'Expense Data'!E:E,A5,'Expense Data'!C:C,"Jul") -> 0 | I5: =SUMIFS('Expense Data'!I:I,'Expense Data'!E:E,A5,'Expense Data'!C:C,"Aug") -> 6544.91 | J5: =SUMIFS('Expense Data'!I:I,'Expense Data'!E:E,A5,'Expense Data'!C:C,"Sep") -> 0 | K5: =SUMIFS('Expense Data'!I:I,'Expense Data'!E:E,A5,'Expense Data'!C:C,"Oct") -> 7104.41 | L5: =SUMIFS('Expense Data'!I:I,'Expense Data'!E:E,A5,'Expense Data'!C:C,"Nov") -> 5312.07 | M5: =SUMIFS('Expense Data'!I:I,'Expense Data'!E:E,A5,'Expense Data'!C:C,"Dec") -> 6854.41 | N5: =SUM(B5:M5) -> 52987.22
A6: Marketing | B6: =SUMIFS('Expense Data'!I:I,'Expense Data'!E:E,A6,'Expense Data'!C:C,"Jan") -> 0 | C6: =SUMIFS('Expense Data'!I:I,'Expense Data'!E:E,A6,'Expense Data'!C:C,"Feb") -> 4582.75 | D6: =SUMIFS('Expense Data'!I:I,'Expense Data'!E:E,A6,'Expense Data'!C:C,"Mar") -> 7942.82 | E6: =SUMIFS('Expense Data'!I:I,'Expense Data'!E:E,A6,'Expense Data'!C:C,"Apr") -> 2125.77 | F6: =SUMIFS('Expense Data'!I:I,'Expense Data'!E:E,A6,'Expense Data'!C:C,"May") -> 2432.93 | G6: =SUMIFS('Expense Data'!I:I,'Expense Data'!E:E,A6,'Expense Data'!C:C,"Jun") -> 0 | H6: =SUMIFS('Expense Data'!I:I,'Expense Data'!E:E,A6,'Expense Data'!C:C,"Jul") -> 5126.22 | I6: =SUMIFS('Expense Data'!I:I,'Expense Data'!E:E,A6,'Expense Data'!C:C,"Aug") -> 7598.74 | J6: =SUMIFS('Expense Data'!I:I,'Expense Data'!E:E,A6,'Expense Data'!C:C,"Sep") -> 8343.65 | K6: =SUMIFS('Expense Data'!I:I,'Expense Data'!E:E,A6,'Expense Data'!C:C,"Oct") -> 2770.16 | L6: =SUMIFS('Expense Data'!I:I,'Expense Data'!E:E,A6,'Expense Data'!C:C,"Nov") -> 11587.95 | M6: =SUMIFS('Expense Data'!I:I,'Expense Data'!E:E,A6,'Expense Data'!C:C,"Dec") -> 3503.75 | N6: =SUM(B6:M6) -> 56014.74
A7: Travel & Expenses | B7: =SUMIFS('Expense Data'!I:I,'Expense Data'!E:E,A7,'Expense Data'!C:C,"Jan") -> 1499.9 | C7: =SUMIFS('Expense Data'!I:I,'Expense Data'!E:E,A7,'Expense Data'!C:C,"Feb") -> 2403.15 | D7: =SUMIFS('Expense Data'!I:I,'Expense Data'!E:E,A7,'Expense Data'!C:C,"Mar") -> 1638.32 | E7: =SUMIFS('Expense Data'!I:I,'Expense Data'!E:E,A7,'Expense Data'!C:C,"Apr") -> 0 | F7: =SUMIFS('Expense Data'!I:I,'Expense Data'!E:E,A7,'Expense Data'!C:C,"May") -> 0 | G7: =SUMIFS('Expense Data'!I:I,'Expense Data'!E:E,A7,'Expense Data'!C:C,"Jun") -> 1271.61 | H7: =SUMIFS('Expense Data'!I:I,'Expense Data'!E:E,A7,'Expense Data'!C:C,"Jul") -> 0 | I7: =SUMIFS('Expense Data'!I:I,'Expense Data'!E:E,A7,'Expense Data'!C:C,"Aug") -> 798.33 | J7: =SUMIFS('Expense Data'!I:I,'Expense Data'!E:E,A7,'Expense Data'!C:C,"Sep") -> 0 | K7: =SUMIFS('Expense Data'!I:I,'Expense Data'!E:E,A7,'Expense Data'!C:C,"Oct") -> 3758.27 | L7: =SUMIFS('Expense Data'!I:I,'Expense Data'!E:E,A7,'Expense Data'!C:C,"Nov") -> 4419.2 | M7: =SUMIFS('Expense Data'!I:I,'Expense Data'!E:E,A7,'Expense Data'!C:C,"Dec") -> 3133.68 | N7: =SUM(B7:M7) -> 18922.46
A8: Office Supplies | B8: =SUMIFS('Expense Data'!I:I,'Expense Data'!E:E,A8,'Expense Data'!C:C,"Jan") -> 1109.42 | C8: =SUMIFS('Expense Data'!I:I,'Expense Data'!E:E,A8,'Expense Data'!C:C,"Feb") -> 791.67 | D8: =SUMIFS('Expense Data'!I:I,'Expense Data'!E:E,A8,'Expense Data'!C:C,"Mar") -> 1328.55 | E8: =SUMIFS('Expense Data'!I:I,'Expense Data'!E:E,A8,'Expense Data'!C:C,"Apr") -> 0 | F8: =SUMIFS('Expense Data'!I:I,'Expense Data'!E:E,A8,'Expense Data'!C:C,"May") -> 0 | G8: =SUMIFS('Expense Data'!I:I,'Expense Data'!E:E,A8,'Expense Data'!C:C,"Jun") -> 755.5 | H8: =SUMIFS('Expense Data'!I:I,'Expense Data'!E:E,A8,'Expense Data'!C:C,"Jul") -> 815.3 | I8: =SUMIFS('Expense Data'!I:I,'Expense Data'!E:E,A8,'Expense Data'!C:C,"Aug") -> 0 | J8: =SUMIFS('Expense Data'!I:I,'Expense Data'!E:E,A8,'Expense Data'!C:C,"Sep") -> 0 | K8: =SUMIFS('Expense Data'!I:I,'Expense Data'!E:E,A8,'Expense Data'!C:C,"Oct") -> 983.16 | L8: =SUMIFS('Expense Data'!I:I,'Expense Data'!E:E,A8,'Expense Data'!C:C,"Nov") -> 624.24 | M8: =SUMIFS('Expense Data'!I:I,'Expense Data'!E:E,A8,'Expense Data'!C:C,"Dec") -> 277.4 | N8: =SUM(B8:M8) -> 6685.24
A9: Professional Services | B9: =SUMIFS('Expense Data'!I:I,'Expense Data'!E:E,A9,'Expense Data'!C:C,"Jan") -> 7540.22 | C9: =SUMIFS('Expense Data'!I:I,'Expense Data'!E:E,A9,'Expense Data'!C:C,"Feb") -> 0 | D9: =SUMIFS('Expense Data'!I:I,'Expense Data'!E:E,A9,'Expense Data'!C:C,"Mar") -> 0 | E9: =SUMIFS('Expense Data'!I:I,'Expense Data'!E:E,A9,'Expense Data'!C:C,"Apr") -> 3728.2 | F9: =SUMIFS('Expense Data'!I:I,'Expense Data'!E:E,A9,'Expense Data'!C:C,"May") -> 0 | G9: =SUMIFS('Expense Data'!I:I,'Expense Data'!E:E,A9,'Expense Data'!C:C,"Jun") -> 0 | H9: =SUMIFS('Expense Data'!I:I,'Expense Data'!E:E,A9,'Expense Data'!C:C,"Jul") -> 0 | I9: =SUMIFS('Expense Data'!I:I,'Expense Data'!E:E,A9,'Expense Data'!C:C,"Aug") -> 6984.85 | J9: =SUMIFS('Expense Data'!I:I,'Expense Data'!E:E,A9,'Expense Data'!C:C,"Sep") -> 5654.1 | K9: =SUMIFS('Expense Data'!I:I,'Expense Data'!E:E,A9,'Expense Data'!C:C,"Oct") -> 2939.56 | L9: =SUMIFS('Expense Data'!I:I,'Expense Data'!E:E,A9,'Expense Data'!C:C,"Nov") -> 3258.64 | M9: =SUMIFS('Expense Data'!I:I,'Expense Data'!E:E,A9,'Expense Data'!C:C,"Dec") -> 5254.29 | N9: =SUM(B9:M9) -> 35359.86
A10: Training & Development | B10: =SUMIFS('Expense Data'!I:I,'Expense Data'!E:E,A10,'Expense Data'!C:C,"Jan") -> 0 | C10: =SUMIFS('Expense Data'!I:I,'Expense Data'!E:E,A10,'Expense Data'!C:C,"Feb") -> 0 | D10: =SUMIFS('Expense Data'!I:I,'Expense Data'!E:E,A10,'Expense Data'!C:C,"Mar") -> 0 | E10: =SUMIFS('Expense Data'!I:I,'Expense Data'!E:E,A10,'Expense Data'!C:C,"Apr") -> 1068.9 | F10: =SUMIFS('Expense Data'!I:I,'Expense Data'!E:E,A10,'Expense Data'!C:C,"May") -> 1947.93 | G10: =SUMIFS('Expense Data'!I:I,'Expense Data'!E:E,A10,'Expense Data'!C:C,"Jun") -> 5155.94 | H10: =SUMIFS('Expense Data'!I:I,'Expense Data'!E:E,A10,'Expense Data'!C:C,"Jul") -> 915.55 | I10: =SUMIFS('Expense Data'!I:I,'Expense Data'!E:E,A10,'Expense Data'!C:C,"Aug") -> 1850.83 | J10: =SUMIFS('Expense Data'!I:I,'Expense Data'!E:E,A10,'Expense Data'!C:C,"Sep") -> 1379.26 | K10: =SUMIFS('Expense Data'!I:I,'Expense Data'!E:E,A10,'Expense Data'!C:C,"Oct") -> 402.88 | L10: =SUMIFS('Expense Data'!I:I,'Expense Data'!E:E,A10,'Expense Data'!C:C,"Nov") -> 0 | M10: =SUMIFS('Expense Data'!I:I,'Expense Data'!E:E,A10,'Expense Data'!C:C,"Dec") -> 0 | N10: =SUM(B10:M10) -> 12721.29
A11: Miscellaneous | B11: =SUMIFS('Expense Data'!I:I,'Expense Data'!E:E,A11,'Expense Data'!C:C,"Jan") -> 0 | C11: =SUMIFS('Expense Data'!I:I,'Expense Data'!E:E,A11,'Expense Data'!C:C,"Feb") -> 651.32 | D11: =SUMIFS('Expense Data'!I:I,'Expense Data'!E:E,A11,'Expense Data'!C:C,"Mar") -> 0 | E11: =SUMIFS('Expense Data'!I:I,'Expense Data'!E:E,A11,'Expense Data'!C:C,"Apr") -> 401.91 | F11: =SUMIFS('Expense Data'!I:I,'Expense Data'!E:E,A11,'Expense Data'!C:C,"May") -> 480.03 | G11: =SUMIFS('Expense Data'!I:I,'Expense Data'!E:E,A11,'Expense Data'!C:C,"Jun") -> 159.97 | H11: =SUMIFS('Expense Data'!I:I,'Expense Data'!E:E,A11,'Expense Data'!C:C,"Jul") -> 536.1 | I11: =SUMIFS('Expense Data'!I:I,'Expense Data'!E:E,A11,'Expense Data'!C:C,"Aug") -> 0 | J11: =SUMIFS('Expense Data'!I:I,'Expense Data'!E:E,A11,'Expense Data'!C:C,"Sep") -> 326.37 | K11: =SUMIFS('Expense Data'!I:I,'Expense Data'!E:E,A11,'Expense Data'!C:C,"Oct") -> 580.68 | L11: =SUMIFS('Expense Data'!I:I,'Expense Data'!E:E,A11,'Expense Data'!C:C,"Nov") -> 131.98 | M11: =SUMIFS('Expense Data'!I:I,'Expense Data'!E:E,A11,'Expense Data'!C:C,"Dec") -> 0 | N11: =SUM(B11:M11) -> 3268.36
A12: GRAND TOTAL | B12: =SUM(B3:B11) -> 57827.47 | C12: =SUM(C3:C11) -> 46342.59 | D12: =SUM(D3:D11) -> 35748.73 | E12: =SUM(E3:E11) -> 31605.33 | F12: =SUM(F3:F11) -> 28228.98 | G12: =SUM(G3:G11) -> 15873.7 | H12: =SUM(H3:H11) -> 28009.23 | I12: =SUM(I3:I11) -> 48110.54 | ... N12: =SUM(N3:N11) -> 440359.69

Sheet KPI Dashboard
A1: SME Expense Tracker — KPI Dashboard 2024
A3: KEY PERFORMANCE INDICATORS
A4: Total Budget (£) | B4: Total Actual (£) | C4: Total Variance (£) | D4: Variance % | E4: Over Budget Items | F4: Under Budget Items | G4: Total Transactions | H4: Avg Transaction (£)
A5: =SUMIF('Expense Data'!E:E,"<>",'Expense Data'!H:H) -> 453193.86 | B5: =SUMIF('Expense Data'!E:E,"<>",'Expense Data'!I:I) -> 440359.69 | C5: =SUMIF('Expense Data'!E:E,"<>",'Expense Data'!J:J) -> -12834.17 | D5: =IFERROR(B8/B6,0) -> 0 | E5: =COUNTIF('Expense Data'!L:L,"Over Budget") -> 32 | F5: =COUNTIF('Expense Data'!L:L,"Under Budget") -> 98 | G5: =COUNTA('Expense Data'!A:A)-1 -> 130 | H5: =IFERROR(B8/B12,0) -> 0
A7: SPEND BY CATEGORY
A8: Category | B8: Budget (£) | C8: Actual (£) | D8: Variance (£) | E8: Variance % | F8: Status
A9: Salaries | B9: =SUMIF('Expense Data'!E:E,A9,'Expense Data'!H:H) -> 199173.41 | C9: =SUMIF('Expense Data'!E:E,A9,'Expense Data'!I:I) -> 201501.93 | D9: =C9-B9 -> 2328.52 | E9: =IFERROR(D9/B9,0) -> 0.011690918 | F9: =IF(D9>0,"Over Budget",IF(D9<0,"Under Budget","On Budget")) -> Over Budget
A10: Rent & Utilities | B10: =SUMIF('Expense Data'!E:E,A10,'Expense Data'!H:H) -> 56011.07 | C10: =SUMIF('Expense Data'!E:E,A10,'Expense Data'!I:I) -> 52898.59 | D10: =C10-B10 -> -3112.48 | E10: =IFERROR(D10/B10,0) -> -0.055569015 | F10: =IF(D10>0,"Over Budget",IF(D10<0,"Under Budget","On Budget")) -> Under Budget
A11: IT & Software | B11: =SUMIF('Expense Data'!E:E,A11,'Expense Data'!H:H) -> 55808.83 | C11: =SUMIF('Expense Data'!E:E,A11,'Expense Data'!I:I) -> 52987.22 | D11: =C11-B11 -> -2821.61 | E11: =IFERROR(D11/B11,0) -> -0.050558487 | F11: =IF(D11>0,"Over Budget",IF(D11<0,"Under Budget","On Budget")) -> Under Budget
A12: Marketing | B12: =SUMIF('Expense Data'!E:E,A12,'Expense Data'!H:H) -> 62112.91 | C12: =SUMIF('Expense Data'!E:E,A12,'Expense Data'!I:I) -> 56014.74 | D12: =C12-B12 -> -6098.17 | E12: =IFERROR(D12/B12,0) -> -0.098178784 | F12: =IF(D12>0,"Over Budget",IF(D12<0,"Under Budget","On Budget")) -> Under Budget
A13: Travel & Expenses | B13: =SUMIF('Expense Data'!E:E,A13,'Expense Data'!H:H) -> 20670.92 | C13: =SUMIF('Expense Data'!E:E,A13,'Expense Data'!I:I) -> 18922.46 | D13: =C13-B13 -> -1748.46 | E13: =IFERROR(D13/B13,0) -> -0.084585495 | F13: =IF(D13>0,"Over Budget",IF(D13<0,"Under Budget","On Budget")) -> Under Budget
A14: Office Supplies | B14: =SUMIF('Expense Data'!E:E,A14,'Expense Data'!H:H) -> 7247.67 | C14: =SUMIF('Expense Data'!E:E,A14,'Expense Data'!I:I) -> 6685.24 | D14: =C14-B14 -> -562.43 | E14: =IFERROR(D14/B14,0) -> -0.077601491 | F14: =IF(D14>0,"Over Budget",IF(D14<0,"Under Budget","On Budget")) -> Under Budget
A15: Professional Services | B15: =SUMIF('Expense Data'!E:E,A15,'Expense Data'!H:H) -> 36906.82 | C15: =SUMIF('Expense Data'!E:E,A15,'Expense Data'!I:I) -> 35359.86 | D15: =C15-B15 -> -1546.96 | E15: =IFERROR(D15/B15,0) -> -0.041915288 | F15: =IF(D15>0,"Over Budget",IF(D15<0,"Under Budget","On Budget")) -> Under Budget
A16: Training & Development | B16: =SUMIF('Expense Data'!E:E,A16,'Expense Data'!H:H) -> 11865.96 | C16: =SUMIF('Expense Data'!E:E,A16,'Expense Data'!I:I) -> 12721.29 | D16: =C16-B16 -> 855.33 | E16: =IFERROR(D16/B16,0) -> 0.072082663 | F16: =IF(D16>0,"Over Budget",IF(D16<0,"Under Budget","On Budget")) -> Over Budget
A17: Miscellaneous | B17: =SUMIF('Expense Data'!E:E,A17,'Expense Data'!H:H) -> 3396.27 | C17: =SUMIF('Expense Data'!E:E,A17,'Expense Data'!I:I) -> 3268.36 | D17: =C17-B17 -> -127.91 | E17: =IFERROR(D17/B17,0) -> -0.037661906 | F17: =IF(D17>0,"Over Budget",IF(D17<0,"Under Budget","On Budget")) -> Under Budget
A18: TOTAL | B18: =SUM(B9:B17) -> 453193.86 | C18: =SUM(C9:C17) -> 440359.69 | D18: =SUM(D9:D17) -> -12834.17 | E18: =SUM(E9:E17) -> -0.36229689

Sheet Budget vs Actual
A1: Budget vs Actual — Monthly P&L View 2024
A2: Category | B2: Jan | D2: Feb | F2: Mar | H2: Apr | J2: May | L2: Jun
B3: Budget £ | C3: Actual £ | D3: Budget £ | E3: Actual £ | F3: Budget £ | G3: Actual £ | H3: Budget £ | I3: Actual £ | J3: Budget £ | K3: Actual £ | L3: Budget £ | M3: Actual £
A4: Salaries | B4: =SUMIFS('Expense Data'!H:H,'Expense Data'!E:E,A4,'Expense Data'!C:C,"Jan") -> 34784.39 | C4: =SUMIFS('Expense Data'!I:I,'Expense Data'!E:E,A4,'Expense Data'!C:C,"Jan") -> 35848.03 | D4: =SUMIFS('Expense Data'!H:H,'Expense Data'!E:E,A4,'Expense Data'!C:C,"Feb") -> 27741.18 | E4: =SUMIFS('Expense Data'!I:I,'Expense Data'!E:E,A4,'Expense Data'!C:C,"Feb") -> 25573.77 | F4: =SUMIFS('Expense Data'!H:H,'Expense Data'!E:E,A4,'Expense Data'!C:C,"Mar") -> 14782.97 | G4: =SUMIFS('Expense Data'!I:I,'Expense Data'!E:E,A4,'Expense Data'!C:C,"Mar") -> 14098.33 | H4: =SUMIFS('Expense Data'!H:H,'Expense Data'!E:E,A4,'Expense Data'!C:C,"Apr") -> 13235.83 | I4: =SUMIFS('Expense Data'!I:I,'Expense Data'!E:E,A4,'Expense Data'!C:C,"Apr") -> 16217.24 | J4: =SUMIFS('Expense Data'!H:H,'Expense Data'!E:E,A4,'Expense Data'!C:C,"May") -> 12281.74 | K4: =SUMIFS('Expense Data'!I:I,'Expense Data'!E:E,A4,'Expense Data'!C:C,"May") -> 11138.98 | L4: =SUMIFS('Expense Data'!H:H,'Expense Data'!E:E,A4,'Expense Data'!C:C,"Jun") -> 0 | M4: =SUMIFS('Expense Data'!I:I,'Expense Data'!E:E,A4,'Expense Data'!C:C,"Jun") -> 0
A5: Rent & Utilities | B5: =SUMIFS('Expense Data'!H:H,'Expense Data'!E:E,A5,'Expense Data'!C:C,"Jan") -> 8055.14 | C5: =SUMIFS('Expense Data'!I:I,'Expense Data'!E:E,A5,'Expense Data'!C:C,"Jan") -> 7303.63 | D5: =SUMIFS('Expense Data'!H:H,'Expense Data'!E:E,A5,'Expense Data'!C:C,"Feb") -> 3115.85 | E5: =SUMIFS('Expense Data'!I:I,'Expense Data'!E:E,A5,'Expense Data'!C:C,"Feb") -> 3045.02 | F5: =SUMIFS('Expense Data'!H:H,'Expense Data'!E:E,A5,'Expense Data'!C:C,"Mar") -> 8102.03 | G5: =SUMIFS('Expense Data'!I:I,'Expense Data'!E:E,A5,'Expense Data'!C:C,"Mar") -> 6525.55 | H5: =SUMIFS('Expense Data'!H:H,'Expense Data'!E:E,A5,'Expense Data'!C:C,"Apr") -> 3309.59 | I5: =SUMIFS('Expense Data'!I:I,'Expense Data'!E:E,A5,'Expense Data'!C:C,"Apr") -> 3251.64 | J5: =SUMIFS('Expense Data'!H:H,'Expense Data'!E:E,A5,'Expense Data'!C:C,"May") -> 8087.26 | K5: =SUMIFS('Expense Data'!I:I,'Expense Data'!E:E,A5,'Expense Data'!C:C,"May") -> 9340.37 | L5: =SUMIFS('Expense Data'!H:H,'Expense Data'!E:E,A5,'Expense Data'!C:C,"Jun") -> 8006.74 | M5: =SUMIFS('Expense Data'!I:I,'Expense Data'!E:E,A5,'Expense Data'!C:C,"Jun") -> 7096.01
A6: IT & Software | B6: =SUMIFS('Expense Data'!H:H,'Expense Data'!E:E,A6,'Expense Data'!C:C,"Jan") -> 4332.08 | C6: =SUMIFS('Expense Data'!I:I,'Expense Data'!E:E,A6,'Expense Data'!C:C,"Jan") -> 4526.27 | D6: =SUMIFS('Expense Data'!H:H,'Expense Data'!E:E,A6,'Expense Data'!C:C,"Feb") -> 9101.37 | E6: =SUMIFS('Expense Data'!I:I,'Expense Data'!E:E,A6,'Expense Data'!C:C,"Feb") -> 9294.91 | F6: =SUMIFS('Expense Data'!H:H,'Expense Data'!E:E,A6,'Expense Data'!C:C,"Mar") -> 4397.5 | G6: =SUMIFS('Expense Data'!I:I,'Expense Data'!E:E,A6,'Expense Data'!C:C,"Mar") -> 4215.16 | H6: =SUMIFS('Expense Data'!H:H,'Expense Data'!E:E,A6,'Expense Data'!C:C,"Apr") -> 3804.12 | I6: =SUMIFS('Expense Data'!I:I,'Expense Data'!E:E,A6,'Expense Data'!C:C,"Apr") -> 4811.67 | J6: =SUMIFS('Expense Data'!H:H,'Expense Data'!E:E,A6,'Expense Data'!C:C,"May") -> 3669.14 | K6: =SUMIFS('Expense Data'!I:I,'Expense Data'!E:E,A6,'Expense Data'!C:C,"May") -> 2888.74 | L6: =SUMIFS('Expense Data'!H:H,'Expense Data'!E:E,A6,'Expense Data'!C:C,"Jun") -> 1667.3 | M6: =SUMIFS('Expense Data'!I:I,'Expense Data'!E:E,A6,'Expense Data'!C:C,"Jun") -> 1434.67
A7: Marketing | B7: =SUMIFS('Expense Data'!H:H,'Expense Data'!E:E,A7,'Expense Data'!C:C,"Jan") -> 0 | C7: =SUMIFS('Expense Data'!I:I,'Expense Data'!E:E,A7,'Expense Data'!C:C,"Jan") -> 0 | D7: =SUMIFS('Expense Data'!H:H,'Expense Data'!E:E,A7,'Expense Data'!C:C,"Feb") -> 3954.42 | E7: =SUMIFS('Expense Data'!I:I,'Expense Data'!E:E,A7,'Expense Data'!C:C,"Feb") -> 4582.75 | F7: =SUMIFS('Expense Data'!H:H,'Expense Data'!E:E,A7,'Expense Data'!C:C,"Mar") -> 10315.14 | G7: =SUMIFS('Expense Data'!I:I,'Expense Data'!E:E,A7,'Expense Data'!C:C,"Mar") -> 7942.82 | H7: =SUMIFS('Expense Data'!H:H,'Expense Data'!E:E,A7,'Expense Data'!C:C,"Apr") -> 2227.52 | I7: =SUMIFS('Expense Data'!I:I,'Expense Data'!E:E,A7,'Expense Data'!C:C,"Apr") -> 2125.77 | J7: =SUMIFS('Expense Data'!H:H,'Expense Data'!E:E,A7,'Expense Data'!C:C,"May") -> 2646.33 | K7: =SUMIFS('Expense Data'!I:I,'Expense Data'!E:E,A7,'Expense Data'!C:C,"May") -> 2432.93 | L7: =SUMIFS('Expense Data'!H:H,'Expense Data'!E:E,A7,'Expense Data'!C:C,"Jun") -> 0 | M7: =SUMIFS('Expense Data'!I:I,'Expense Data'!E:E,A7,'Expense Data'!C:C,"Jun") -> 0
A8: Travel & Expenses | B8: =SUMIFS('Expense Data'!H:H,'Expense Data'!E:E,A8,'Expense Data'!C:C,"Jan") -> 1782.98 | C8: =SUMIFS('Expense Data'!I:I,'Expense Data'!E:E,A8,'Expense Data'!C:C,"Jan") -> 1499.9 | D8: =SUMIFS('Expense Data'!H:H,'Expense Data'!E:E,A8,'Expense Data'!C:C,"Feb") -> 2930.8 | E8: =SUMIFS('Expense Data'!I:I,'Expense Data'!E:E,A8,'Expense Data'!C:C,"Feb") -> 2403.15 | F8: =SUMIFS('Expense Data'!H:H,'Expense Data'!E:E,A8,'Expense Data'!C:C,"Mar") -> 1503.47 | G8: =SUMIFS('Expense Data'!I:I,'Expense Data'!E:E,A8,'Expense Data'!C:C,"Mar") -> 1638.32 | H8: =SUMIFS('Expense Data'!H:H,'Expense Data'!E:E,A8,'Expense Data'!C:C,"Apr") -> 0 | I8: =SUMIFS('Expense Data'!I:I,'Expense Data'!E:E,A8,'Expense Data'!C:C,"Apr") -> 0 | J8: =SUMIFS('Expense Data'!H:H,'Expense Data'!E:E,A8,'Expense Data'!C:C,"May") -> 0 | K8: =SUMIFS('Expense Data'!I:I,'Expense Data'!E:E,A8,'Expense Data'!C:C,"May") -> 0 | L8: =SUMIFS('Expense Data'!H:H,'Expense Data'!E:E,A8,'Expense Data'!C:C,"Jun") -> 1523.1 | M8: =SUMIFS('Expense Data'!I:I,'Expense Data'!E:E,A8,'Expense Data'!C:C,"Jun") -> 1271.61
A9: Office Supplies | B9: =SUMIFS('Expense Data'!H:H,'Expense Data'!E:E,A9,'Expense Data'!C:C,"Jan") -> 1308.2 | C9: =SUMIFS('Expense Data'!I:I,'Expense Data'!E:E,A9,'Expense Data'!C:C,"Jan") -> 1109.42 | D9: =SUMIFS('Expense Data'!H:H,'Expense Data'!E:E,A9,'Expense Data'!C:C,"Feb") -> 971.93 | E9: =SUMIFS('Expense Data'!I:I,'Expense Data'!E:E,A9,'Expense Data'!C:C,"Feb") -> 791.67 | F9: =SUMIFS('Expense Data'!H:H,'Expense Data'!E:E,A9,'Expense Data'!C:C,"Mar") -> 1171.74 | G9: =SUMIFS('Expense Data'!I:I,'Expense Data'!E:E,A9,'Expense Data'!C:C,"Mar") -> 1328.55 | H9: =SUMIFS('Expense Data'!H:H,'Expense Data'!E:E,A9,'Expense Data'!C:C,"Apr") -> 0 | I9: =SUMIFS('Expense Data'!I:I,'Expense Data'!E:E,A9,'Expense Data'!C:C,"Apr") -> 0 | J9: =SUMIFS('Expense Data'!H:H,'Expense Data'!E:E,A9,'Expense Data'!C:C,"May") -> 0 | K9: =SUMIFS('Expense Data'!I:I,'Expense Data'!E:E,A9,'Expense Data'!C:C,"May") -> 0 | L9: =SUMIFS('Expense Data'!H:H,'Expense Data'!E:E,A9,'Expense Data'!C:C,"Jun") -> 785.72 | M9: =SUMIFS('Expense Data'!I:I,'Expense Data'!E:E,A9,'Expense Data'!C:C,"Jun") -> 755.5
A10: Professional Services | B10: =SUMIFS('Expense Data'!H:H,'Expense Data'!E:E,A10,'Expense Data'!C:C,"Jan") -> 7909.49 | C10: =SUMIFS('Expense Data'!I:I,'Expense Data'!E:E,A10,'Expense Data'!C:C,"Jan") -> 7540.22 | D10: =SUMIFS('Expense Data'!H:H,'Expense Data'!E:E,A10,'Expense Data'!C:C,"Feb") -> 0 | E10: =SUMIFS('Expense Data'!I:I,'Expense Data'!E:E,A10,'Expense Data'!C:C,"Feb") -> 0 | F10: =SUMIFS('Expense Data'!H:H,'Expense Data'!E:E,A10,'Expense Data'!C:C,"Mar") -> 0 | G10: =SUMIFS('Expense Data'!I:I,'Expense Data'!E:E,A10,'Expense Data'!C:C,"Mar") -> 0 | H10: =SUMIFS('Expense Data'!H:H,'Expense Data'!E:E,A10,'Expense Data'!C:C,"Apr") -> 4417.85 | I10: =SUMIFS('Expense Data'!I:I,'Expense Data'!E:E,A10,'Expense Data'!C:C,"Apr") -> 3728.2 | J10: =SUMIFS('Expense Data'!H:H,'Expense Data'!E:E,A10,'Expense Data'!C:C,"May") -> 0 | K10: =SUMIFS('Expense Data'!I:I,'Expense Data'!E:E,A10,'Expense Data'!C:C,"May") -> 0 | L10: =SUMIFS('Expense Data'!H:H,'Expense Data'!E:E,A10,'Expense Data'!C:C,"Jun") -> 0 | M10: =SUMIFS('Expense Data'!I:I,'Expense Data'!E:E,A10,'Expense Data'!C:C,"Jun") -> 0
A11: Training & Development | B11: =SUMIFS('Expense Data'!H:H,'Expense Data'!E:E,A11,'Expense Data'!C:C,"Jan") -> 0 | C11: =SUMIFS('Expense Data'!I:I,'Expense Data'!E:E,A11,'Expense Data'!C:C,"Jan") -> 0 | D11: =SUMIFS('Expense Data'!H:H,'Expense Data'!E:E,A11,'Expense Data'!C:C,"Feb") -> 0 | E11: =SUMIFS('Expense Data'!I:I,'Expense Data'!E:E,A11,'Expense Data'!C:C,"Feb") -> 0 | F11: =SUMIFS('Expense Data'!H:H,'Expense Data'!E:E,A11,'Expense Data'!C:C,"Mar") -> 0 | G11: =SUMIFS('Expense Data'!I:I,'Expense Data'!E:E,A11,'Expense Data'!C:C,"Mar") -> 0 | H11: =SUMIFS('Expense Data'!H:H,'Expense Data'!E:E,A11,'Expense Data'!C:C,"Apr") -> 994.7 | I11: =SUMIFS('Expense Data'!I:I,'Expense Data'!E:E,A11,'Expense Data'!C:C,"Apr") -> 1068.9 | J11: =SUMIFS('Expense Data'!H:H,'Expense Data'!E:E,A11,'Expense Data'!C:C,"May") -> 1896.57 | K11: =SUMIFS('Expense Data'!I:I,'Expense Data'!E:E,A11,'Expense Data'!C:C,"May") -> 1947.93 | L11: =SUMIFS('Expense Data'!H:H,'Expense Data'!E:E,A11,'Expense Data'!C:C,"Jun") -> 4355.95 | M11: =SUMIFS('Expense Data'!I:I,'Expense Data'!E:E,A11,'Expense Data'!C:C,"Jun") -> 5155.94
A12: Miscellaneous | B12: =SUMIFS('Expense Data'!H:H,'Expense Data'!E:E,A12,'Expense Data'!C:C,"Jan") -> 0 | C12: =SUMIFS('Expense Data'!I:I,'Expense Data'!E:E,A12,'Expense Data'!C:C,"Jan") -> 0 | D12: =SUMIFS('Expense Data'!H:H,'Expense Data'!E:E,A12,'Expense Data'!C:C,"Feb") -> 742.16 | E12: =SUMIFS('Expense Data'!I:I,'Expense Data'!E:E,A12,'Expense Data'!C:C,"Feb") -> 651.32 | F12: =SUMIFS('Expense Data'!H:H,'Expense Data'!E:E,A12,'Expense Data'!C:C,"Mar") -> 0 | G12: =SUMIFS('Expense Data'!I:I,'Expense Data'!E:E,A12,'Expense Data'!C:C,"Mar") -> 0 | H12: =SUMIFS('Expense Data'!H:H,'Expense Data'!E:E,A12,'Expense Data'!C:C,"Apr") -> 370.09 | I12: =SUMIFS('Expense Data'!I:I,'Expense Data'!E:E,A12,'Expense Data'!C:C,"Apr") -> 401.91 | J12: =SUMIFS('Expense Data'!H:H,'Expense Data'!E:E,A12,'Expense Data'!C:C,"May") -> 387.04 | K12: =SUMIFS('Expense Data'!I:I,'Expense Data'!E:E,A12,'Expense Data'!C:C,"May") -> 480.03 | L12: =SUMIFS('Expense Data'!H:H,'Expense Data'!E:E,A12,'Expense Data'!C:C,"Jun") -> 189.17 | M12: =SUMIFS('Expense Data'!I:I,'Expense Data'!E:E,A12,'Expense Data'!C:C,"Jun") -> 159.97

Sheet Instructions
A1: How to Use This Workbook
A2: Step | B2: Sheet | C2: Action | D2: Input Cells
A3: 1 | B3: Expense Data | C3: Add new expense rows below existing data. Fill columns B–I only. Columns J–L calculate automatically. | D3: B:I
A4: 2 | B4: Expense Data | C4: Column H = Budget amount. Column I = Actual amount. Column J–L are formulas — do not edit. | D4: H, I
A5: 3 | B5: Monthly Summary | C5: This sheet updates automatically from Expense Data. No manual input needed. | D5: Read only
A6: 4 | B6: KPI Dashboard | C6: All KPIs update automatically. Review category over/under budget status. | D6: Read only
A7: 5 | B7: Budget vs Actual | C7: H1 comparison (Jan–Jun) updates automatically. Extend to H2 (Jul–Dec) by adding more columns. | D7: Read only
