Workbook

Sheet Workforce Data
A1: Workforce Headcount & Cost Data | FY 2024 | 201 Employees
A2: Source table | Do not edit — use Scenario Planner to model changes
A3: Emp ID | B3: Dept ID | C3: Department | D3: Division | E3: Reports To | F3: Level | G3: Level Name | H3: Base Salary | I3: Bonus | J3: Benefits | K3: Total Cost | L3: Bonus % | M3: Start Date | N3: Start Year | O3: Tenure (Yrs) | P3: Status | Q3: Location | R3: Gender | S3: Full Time | T3: HC Flag
A4: EMP-0001 | B4: D001 | C4: Engineering | D4: Technology | E4: CTO | F4: L1 | G4: Junior | H4: 51800 | I4: 0 | J4: 9300 | K4: 61100 | L4: 0 | M4: 2022-05-01 | N4: 2022 | O4: 2.7 | P4: Active | Q4: London | R4: F | S4: 1 | T4: 1
A5: EMP-0002 | B5: D001 | C5: Engineering | D5: Technology | E5: CTO | F5: L2 | G5: Mid-Level | H5: 70900 | I5: 3500 | J5: 12800 | K5: 87200 | L5: 5 | M5: 2020-03-01 | N5: 2020 | O5: 4.8 | P5: Active | Q5: Remote | R5: F | S5: 1 | T5: 1
A6: EMP-0003 | B6: D001 | C6: Engineering | D6: Technology | E6: CTO | F6: L2 | G6: Mid-Level | H6: 71600 | I6: 3600 | J6: 12900 | K6: 88100 | L6: 5 | M6: 2019-10-01 | N6: 2019 | O6: 5.3 | P6: Active | Q6: London | R6: M | S6: 1 | T6: 1
A7: EMP-0004 | B7: D001 | C7: Engineering | D7: Technology | E7: CTO | F7: L3 | G7: Senior | H7: 96600 | I7: 7700 | J7: 17400 | K7: 121700 | L7: 8 | M7: 2019-11-01 | N7: 2019 | O7: 5.2 | P7: Active | Q7: Manchester | R7: M | S7: 1 | T7: 1
A8: EMP-0005 | B8: D001 | C8: Engineering | D8: Technology | E8: CTO | F8: L3 | G8: Senior | H8: 89100 | I8: 7100 | J8: 16000 | K8: 112200 | L8: 8 | M8: 2022-01-01 | N8: 2022 | O8: 3 | P8: Active | Q8: Birmingham | R8: Non-binary | S8: 1 | T8: 1
A9: EMP-0006 | B9: D001 | C9: Engineering | D9: Technology | E9: CTO | F9: L2 | G9: Mid-Level | H9: 67700 | I9: 3400 | J9: 12200 | K9: 83300 | L9: 5 | M9: 2023-10-01 | N9: 2023 | O9: 1.3 | P9: Active | Q9: London | R9: F | S9: 0 | T9: 1
A10: EMP-0007 | B10: D001 | C10: Engineering | D10: Technology | E10: CTO | F10: L3 | G10: Senior | H10: 88400 | I10: 7100 | J10: 15900 | K10: 111400 | L10: 8 | M10: 2023-11-01 | N10: 2023 | O10: 1.2 | P10: On Leave | Q10: Remote | R10: F | S10: 1 | T10: 1
A11: EMP-0008 | B11: D001 | C11: Engineering | D11: Technology | E11: CTO | F11: L1 | G11: Junior | H11: 59200 | I11: 0 | J11: 10700 | K11: 69900 | L11: 0 | M11: 2020-12-01 | N11: 2020 | O11: 4.1 | P11: Active | Q11: Edinburgh | R11: F | S11: 1 | T11: 1
A12: EMP-0009 | B12: D001 | C12: Engineering | D12: Technology | E12: CTO | F12: L2 | G12: Mid-Level | H12: 64900 | I12: 3200 | J12: 11700 | K12: 79800 | L12: 5 | M12: 2019-12-01 | N12: 2019 | O12: 5.1 | P12: On Leave | Q12: Edinburgh | R12: Non-binary | S12: 1 | T12: 1
A13: EMP-0010 | B13: D001 | C13: Engineering | D13: Technology | E13: CTO | F13: L1 | G13: Junior | H13: 57300 | I13: 0 | J13: 10300 | K13: 67600 | L13: 0 | M13: 2024-06-01 | N13: 2024 | O13: 0.6 | P13: Active | Q13: Birmingham | R13: M | S13: 1 | T13: 1
A14: EMP-0011 | B14: D001 | C14: Engineering | D14: Technology | E14: CTO | F14: L3 | G14: Senior | H14: 95200 | I14: 7600 | J14: 17100 | K14: 119900 | L14: 8 | M14: 2019-11-01 | N14: 2019 | O14: 5.2 | P14: Active | Q14: Edinburgh | R14: M | S14: 1 | T14: 1
A15: EMP-0012 | B15: D001 | C15: Engineering | D15: Technology | E15: CTO | F15: L6 | G15: Director | H15: 173000 | I15: 34600 | J15: 31100 | K15: 238700 | L15: 20 | M15: 2023-08-01 | N15: 2023 | O15: 1.4 | P15: Active | Q15: Edinburgh | R15: M | S15: 1 | T15: 1
... A204: EMP-0201 | B204: D010 | C204: Operations | D204: Operations | E204: COO | F204: L2 | G204: Mid-Level | H204: 43900 | I204: 2200 | J204: 7900 | K204: 54000 | L204: 5 | M204: 2024-02-01 | N204: 2024 | O204: 0.9 | P204: Contractor | Q204: London | R204: F | S204: 1 | T204: 0

Sheet Scenario Planner
A1: Workforce Cost Scenario Planner | What-If Analysis
A2: Change the yellow input cells to model different hiring and salary scenarios
A4: BASELINE — CURRENT STATE | G4: SCENARIO INPUTS ← Change yellow cells
A5: Total Headcount | B5: =COUNTIF('Workforce Data'!T4:T204,1) -> 179 | G5: Headcount change (%) | H5: 0.1 | I5: e.g. 0.10 = hire 10% more staff
A6: Total Base Salary | B6: =SUMIF('Workforce Data'!T4:T204,1,'Workforce Data'!H4:H204) -> 13408100 | G6: Salary increase (%) | H6: 0.05 | I6: Annual pay rise across all staff
A7: Total Bonus Cost | B7: =SUMIF('Workforce Data'!T4:T204,1,'Workforce Data'!I4:I204) -> 1317200 | G7: Bonus change (%) | H7: 0 | I7: Change to bonus pool (+ or -)
A8: Total Benefits Cost | B8: =SUMIF('Workforce Data'!T4:T204,1,'Workforce Data'!J4:J204) -> 2413600 | G8: New hire avg salary (£) | H8: 65000 | I8: Average salary for new hires
A9: Total People Cost | B9: =SUMIF('Workforce Data'!T4:T204,1,'Workforce Data'!K4:K204) -> 17138900 | G9: Benefits rate (%) | H9: 0.18 | I9: Benefits as % of base salary
A10: Avg Cost Per Employee | B10: =IFERROR(B9/B5,0) -> 95748.045 | G10: Scenario name | H10: Growth +10% | I10: Label for this scenario
A12: SCENARIO RESULTS — MODELLED STATE | G12: VARIANCE vs BASELINE
A13: Scenario Headcount | B13: =ROUND(B5*(1+H5),0) -> 197 | G13: vs Baseline HC | H13: =B13-B5 -> 18 | I13: =IFERROR(B13/B5-1,0) -> 0.10055866
A14: New Hires | B14: =MAX(0,B13-B5) -> 18 | G14: New Hire Cost | H14: =B14*H8 -> 1170000 | I14: ""
A15: Scenario Base Salary | B15: =B6*(1+H6)+B14*H8 -> 15248505 | G15: Salary Delta | H15: =B15-B6 -> 1840405 | I15: =IFERROR(B15/B6-1,0) -> 0.13726069
A16: Scenario Bonus | B16: =B7*(1+H7) -> 1317200 | G16: Bonus Delta | H16: =B16-B7 -> 0 | I16: =IFERROR(B16/B7-1,0) -> 0
A17: Scenario Benefits | B17: =(B15+B14*H8)*H9 -> 2955330.9 | G17: Benefits Delta | H17: =B17-B8 -> 541730.9 | I17: =IFERROR(B17/B8-1,0) -> 0.22444933
A18: Scenario Total Cost | B18: =B15+B16+B17 -> 19521036 | G18: TOTAL COST DELTA | H18: =B18-B9 -> 2382135.9 | I18: =IFERROR(B18/B9-1,0) -> 0.13899001
A19: Cost Per Employee | B19: =IFERROR(B18/B13,0) -> 99091.553 | G19: Cost Per Head Δ | H19: =B19-B10 -> 3343.5081 | I19: =IFERROR(B19/B10-1,0) -> 0.034919858
A22: =CONCATENATE("Scenario: ",H10," | Headcount: ",TEXT(B13,"#,##0")," | Total Cost: £",TEXT(B18,"#,##0")," | vs Baseline: £",TEXT(B20,"+#,##0;-#,##0")) -> Scenario: Growth +10% | Headcount: 197 | Total Cost: £19,521,036 | vs Baseline: £+0
A24: PRESET SCENARIOS — Compare three strategies side by side
A25: Metric | B25: Freeze Headcount | C25: Growth +10% | D25: Rapid Growth +25% | E25: Cost Reduction -10%
A26: Headcount | B26: 201 | C26: 221 | D26: 251 | E26: 181
A27: Base Salary (£) | B27: £14,118,000 | C27: £15,545,000 | D27: £17,651,000 | E27: £12,706,000
A28: Bonus Cost (£) | B28: £1,236,000 | C28: £1,360,000 | D28: £1,544,000 | E28: £1,112,000
A29: Benefits (£) | B29: £2,541,000 | C29: £2,930,000 | D29: £3,591,000 | E29: £2,287,000
A30: Total Cost (£) | B30: £17,895,000 | C30: £19,835,000 | D30: £22,786,000 | E30: £16,105,000
A31: vs Baseline | B31: -£1,304,000 | C31: +£636,000 | D31: +£3,587,000 | E31: -£3,094,000
A32: Cost per head (£) | B32: £89,030 | C32: £89,752 | D32: £90,781 | E32: £88,978
A33: Scenario type | B33: Defensive | C33: Moderate growth | D33: Aggressive | E33: Cost-saving

Sheet Headcount Dashboard
A1: Headcount & Cost Dashboard | Current State Analysis | FY 2024
A3: TOTAL HEADCOUNT | C3: TOTAL COST | E3: AVG BASE SALARY | G3: CONTRACTORS | I3: AVG TENURE | K3: REMOTE
A5: =COUNTIF('Workforce Data'!T4:T204,1) -> 179 | C5: =SUMIF('Workforce Data'!T4:T204,1,'Workforce Data'!K4:K204) -> 17138900 | E5: =IFERROR(SUMIF('Workforce Data'!T4:T204,1,'Workforce Data'!H4:H204)/COUNTIF('Workforce Data'!T4:T204,1),0) -> 74905.587 | G5: =COUNTIF('Workforce Data'!P4:P204,"Contractor") -> 22 | I5: =IFERROR(AVERAGEIF('Workforce Data'!T4:T204,1,'Workforce Data'!O4:O204),0) -> 3.0977654 | K5: =COUNTIF('Workforce Data'!Q4:Q204,"Remote") -> 30
A10: DEPARTMENT SUMMARY
A11: Department | B11: Division | C11: Headcount | D11: Base Salary | E11: Bonus | F11: Benefits | G11: Total Cost | H11: Cost/Head | I11: Avg Tenure | J11: % of HC
A12: Engineering | B12: Technology | C12: =COUNTIF('Workforce Data'!C:C,"Engineering") -> 45 | D12: =SUMIF('Workforce Data'!C:C,"Engineering",'Workforce Data'!H:H) -> 3946100 | E12: =SUMIF('Workforce Data'!C:C,"Engineering",'Workforce Data'!I:I) -> 356800 | F12: =SUMIF('Workforce Data'!C:C,"Engineering",'Workforce Data'!J:J) -> 710200 | G12: =SUMIF('Workforce Data'!C:C,"Engineering",'Workforce Data'!K:K) -> 5013100 | H12: =IFERROR(G12/C12,0) -> 111402.22 | I12: =IFERROR(AVERAGEIF('Workforce Data'!C:C,"Engineering",'Workforce Data'!O:O),0) -> 2.7933333 | J12: =IFERROR(C12/C22,0) -> 0.2238806
A13: Product | B13: Technology | C13: =COUNTIF('Workforce Data'!C:C,"Product") -> 18 | D13: =SUMIF('Workforce Data'!C:C,"Product",'Workforce Data'!H:H) -> 1345000 | E13: =SUMIF('Workforce Data'!C:C,"Product",'Workforce Data'!I:I) -> 97100 | F13: =SUMIF('Workforce Data'!C:C,"Product",'Workforce Data'!J:J) -> 242000 | G13: =SUMIF('Workforce Data'!C:C,"Product",'Workforce Data'!K:K) -> 1684100 | H13: =IFERROR(G13/C13,0) -> 93561.111 | I13: =IFERROR(AVERAGEIF('Workforce Data'!C:C,"Product",'Workforce Data'!O:O),0) -> 3.9611111 | J13: =IFERROR(C13/C22,0) -> 0.089552239
A14: Data & Analytics | B14: Technology | C14: =COUNTIF('Workforce Data'!C:C,"Data & Analytics") -> 12 | D14: =SUMIF('Workforce Data'!C:C,"Data & Analytics",'Workforce Data'!H:H) -> 1129200 | E14: =SUMIF('Workforce Data'!C:C,"Data & Analytics",'Workforce Data'!I:I) -> 131400 | F14: =SUMIF('Workforce Data'!C:C,"Data & Analytics",'Workforce Data'!J:J) -> 203200 | G14: =SUMIF('Workforce Data'!C:C,"Data & Analytics",'Workforce Data'!K:K) -> 1463800 | H14: =IFERROR(G14/C14,0) -> 121983.33 | I14: =IFERROR(AVERAGEIF('Workforce Data'!C:C,"Data & Analytics",'Workforce Data'!O:O),0) -> 2.85 | J14: =IFERROR(C14/C22,0) -> 0.059701493
A15: Sales | B15: Revenue | C15: =COUNTIF('Workforce Data'!C:C,"Sales") -> 35 | D15: =SUMIF('Workforce Data'!C:C,"Sales",'Workforce Data'!H:H) -> 2376700 | E15: =SUMIF('Workforce Data'!C:C,"Sales",'Workforce Data'!I:I) -> 261400 | F15: =SUMIF('Workforce Data'!C:C,"Sales",'Workforce Data'!J:J) -> 428000 | G15: =SUMIF('Workforce Data'!C:C,"Sales",'Workforce Data'!K:K) -> 3066100 | H15: =IFERROR(G15/C15,0) -> 87602.857 | I15: =IFERROR(AVERAGEIF('Workforce Data'!C:C,"Sales",'Workforce Data'!O:O),0) -> 2.6857143 | J15: =IFERROR(C15/C22,0) -> 0.17412935
A16: Marketing | B16: Revenue | C16: =COUNTIF('Workforce Data'!C:C,"Marketing") -> 20 | D16: =SUMIF('Workforce Data'!C:C,"Marketing",'Workforce Data'!H:H) -> 1457000 | E16: =SUMIF('Workforce Data'!C:C,"Marketing",'Workforce Data'!I:I) -> 150700 | F16: =SUMIF('Workforce Data'!C:C,"Marketing",'Workforce Data'!J:J) -> 262200 | G16: =SUMIF('Workforce Data'!C:C,"Marketing",'Workforce Data'!K:K) -> 1869900 | H16: =IFERROR(G16/C16,0) -> 93495 | I16: =IFERROR(AVERAGEIF('Workforce Data'!C:C,"Marketing",'Workforce Data'!O:O),0) -> 3.695 | J16: =IFERROR(C16/C22,0) -> 0.099502488
A17: Customer Success | B17: Revenue | C17: =COUNTIF('Workforce Data'!C:C,"Customer Success") -> 25 | D17: =SUMIF('Workforce Data'!C:C,"Customer Success",'Workforce Data'!H:H) -> 1439500 | E17: =SUMIF('Workforce Data'!C:C,"Customer Success",'Workforce Data'!I:I) -> 136900 | F17: =SUMIF('Workforce Data'!C:C,"Customer Success",'Workforce Data'!J:J) -> 259100 | G17: =SUMIF('Workforce Data'!C:C,"Customer Success",'Workforce Data'!K:K) -> 1835500 | H17: =IFERROR(G17/C17,0) -> 73420 | I17: =IFERROR(AVERAGEIF('Workforce Data'!C:C,"Customer Success",'Workforce Data'!O:O),0) -> 2.812 | J17: =IFERROR(C17/C22,0) -> 0.12437811
A18: Finance | B18: Operations | C18: =COUNTIF('Workforce Data'!C:C,"Finance") -> 12 | D18: =SUMIF('Workforce Data'!C:C,"Finance",'Workforce Data'!H:H) -> 909800 | E18: =SUMIF('Workforce Data'!C:C,"Finance",'Workforce Data'!I:I) -> 92500 | F18: =SUMIF('Workforce Data'!C:C,"Finance",'Workforce Data'!J:J) -> 163800 | G18: =SUMIF('Workforce Data'!C:C,"Finance",'Workforce Data'!K:K) -> 1166100 | H18: =IFERROR(G18/C18,0) -> 97175 | I18: =IFERROR(AVERAGEIF('Workforce Data'!C:C,"Finance",'Workforce Data'!O:O),0) -> 3.7916667 | J18: =IFERROR(C18/C22,0) -> 0.059701493
A19: HR & People | B19: Operations | C19: =COUNTIF('Workforce Data'!C:C,"HR & People") -> 8 | D19: =SUMIF('Workforce Data'!C:C,"HR & People",'Workforce Data'!H:H) -> 671400 | E19: =SUMIF('Workforce Data'!C:C,"HR & People",'Workforce Data'!I:I) -> 89300 | F19: =SUMIF('Workforce Data'!C:C,"HR & People",'Workforce Data'!J:J) -> 120900 | G19: =SUMIF('Workforce Data'!C:C,"HR & People",'Workforce Data'!K:K) -> 881600 | H19: =IFERROR(G19/C19,0) -> 110200 | I19: =IFERROR(AVERAGEIF('Workforce Data'!C:C,"HR & People",'Workforce Data'!O:O),0) -> 3.2625 | J19: =IFERROR(C19/C22,0) -> 0.039800995
A20: Legal | B20: Operations | C20: =COUNTIF('Workforce Data'!C:C,"Legal") -> 6 | D20: =SUMIF('Workforce Data'!C:C,"Legal",'Workforce Data'!H:H) -> 471500 | E20: =SUMIF('Workforce Data'!C:C,"Legal",'Workforce Data'!I:I) -> 29000 | F20: =SUMIF('Workforce Data'!C:C,"Legal",'Workforce Data'!J:J) -> 84900 | G20: =SUMIF('Workforce Data'!C:C,"Legal",'Workforce Data'!K:K) -> 585400 | H20: =IFERROR(G20/C20,0) -> 97566.667 | I20: =IFERROR(AVERAGEIF('Workforce Data'!C:C,"Legal",'Workforce Data'!O:O),0) -> 2.2166667 | J20: =IFERROR(C20/C22,0) -> 0.029850746
A21: Operations | B21: Operations | C21: =COUNTIF('Workforce Data'!C:C,"Operations") -> 20 | D21: =SUMIF('Workforce Data'!C:C,"Operations",'Workforce Data'!H:H) -> 1270000 | E21: =SUMIF('Workforce Data'!C:C,"Operations",'Workforce Data'!I:I) -> 135000 | F21: =SUMIF('Workforce Data'!C:C,"Operations",'Workforce Data'!J:J) -> 228600 | G21: =SUMIF('Workforce Data'!C:C,"Operations",'Workforce Data'!K:K) -> 1633600 | H21: =IFERROR(G21/C21,0) -> 81680 | I21: =IFERROR(AVERAGEIF('Workforce Data'!C:C,"Operations",'Workforce Data'!O:O),0) -> 3.325 | J21: =IFERROR(C21/C22,0) -> 0.099502488
A22: TOTAL | B22: All | C22: =SUM(C12:C21) -> 201 | D22: =SUM(D12:D21) -> 15016200 | E22: =SUM(E12:E21) -> 1480100 | F22: =SUM(F12:F21) -> 2702900 | G22: =SUM(G12:G21) -> 19199200 | H22: =IFERROR(G22/C22,0) -> 95518.408 | I22: =IFERROR(AVERAGE(J12:J21),0) -> 0.1 | J22: 1

Sheet Level Analysis
A1: Workforce Level & Grade Analysis | Salary Band Review
A2: Level | B2: Level Name | C2: Headcount | D2: Avg Base Salary | E2: Min Salary | F2: Max Salary | G2: Total Cost
A3: L1 | B3: Junior | C3: =COUNTIF('Workforce Data'!F:F,"L1") -> 26 | D3: =IFERROR(AVERAGEIF('Workforce Data'!F:F,"L1",'Workforce Data'!H:H),0) -> 50138.462 | E3: =IFERROR(minifs('Workforce Data'!H:H,'Workforce Data'!F:F,"L1"),0) -> 0 | F3: =IFERROR(maxifs('Workforce Data'!H:H,'Workforce Data'!F:F,"L1"),0) -> 0 | G3: =SUMIF('Workforce Data'!F:F,"L1",'Workforce Data'!K:K) -> 1538500
A4: L2 | B4: Mid-Level | C4: =COUNTIF('Workforce Data'!F:F,"L2") -> 60 | D4: =IFERROR(AVERAGEIF('Workforce Data'!F:F,"L2",'Workforce Data'!H:H),0) -> 54458.333 | E4: =IFERROR(minifs('Workforce Data'!H:H,'Workforce Data'!F:F,"L2"),0) -> 0 | F4: =IFERROR(maxifs('Workforce Data'!H:H,'Workforce Data'!F:F,"L2"),0) -> 0 | G4: =SUMIF('Workforce Data'!F:F,"L2",'Workforce Data'!K:K) -> 4019000
A5: L3 | B5: Senior | C5: =COUNTIF('Workforce Data'!F:F,"L3") -> 58 | D5: =IFERROR(AVERAGEIF('Workforce Data'!F:F,"L3",'Workforce Data'!H:H),0) -> 72348.276 | E5: =IFERROR(minifs('Workforce Data'!H:H,'Workforce Data'!F:F,"L3"),0) -> 0 | F5: =IFERROR(maxifs('Workforce Data'!H:H,'Workforce Data'!F:F,"L3"),0) -> 0 | G5: =SUMIF('Workforce Data'!F:F,"L3",'Workforce Data'!K:K) -> 5287000
A6: L4 | B6: Lead | C6: =COUNTIF('Workforce Data'!F:F,"L4") -> 27 | D6: =IFERROR(AVERAGEIF('Workforce Data'!F:F,"L4",'Workforce Data'!H:H),0) -> 87970.37 | E6: =IFERROR(minifs('Workforce Data'!H:H,'Workforce Data'!F:F,"L4"),0) -> 0 | F6: =IFERROR(maxifs('Workforce Data'!H:H,'Workforce Data'!F:F,"L4"),0) -> 0 | G6: =SUMIF('Workforce Data'!F:F,"L4",'Workforce Data'!K:K) -> 3087900
A7: L5 | B7: Manager | C7: =COUNTIF('Workforce Data'!F:F,"L5") -> 18 | D7: =IFERROR(AVERAGEIF('Workforce Data'!F:F,"L5",'Workforce Data'!H:H),0) -> 112211.11 | E7: =IFERROR(minifs('Workforce Data'!H:H,'Workforce Data'!F:F,"L5"),0) -> 0 | F7: =IFERROR(maxifs('Workforce Data'!H:H,'Workforce Data'!F:F,"L5"),0) -> 0 | G7: =SUMIF('Workforce Data'!F:F,"L5",'Workforce Data'!K:K) -> 2686400
A8: L6 | B8: Director | C8: =COUNTIF('Workforce Data'!F:F,"L6") -> 10 | D8: =IFERROR(AVERAGEIF('Workforce Data'!F:F,"L6",'Workforce Data'!H:H),0) -> 140860 | E8: =IFERROR(minifs('Workforce Data'!H:H,'Workforce Data'!F:F,"L6"),0) -> 0 | F8: =IFERROR(maxifs('Workforce Data'!H:H,'Workforce Data'!F:F,"L6"),0) -> 0 | G8: =SUMIF('Workforce Data'!F:F,"L6",'Workforce Data'!K:K) -> 1943700
A9: L7 | B9: VP | C9: =COUNTIF('Workforce Data'!F:F,"L7") -> 2 | D9: =IFERROR(AVERAGEIF('Workforce Data'!F:F,"L7",'Workforce Data'!H:H),0) -> 222650 | E9: =IFERROR(minifs('Workforce Data'!H:H,'Workforce Data'!F:F,"L7"),0) -> 0 | F9: =IFERROR(maxifs('Workforce Data'!H:H,'Workforce Data'!F:F,"L7"),0) -> 0 | G9: =SUMIF('Workforce Data'!F:F,"L7",'Workforce Data'!K:K) -> 636700
